{"모욕": 2, "욕설": 0, "외설": 0, "폭력위협/범죄조장": 0, "성혐오": 0, "연령": 0, "인종/지역": 1, "장애": 0, "종교": 0, "정치성향": 1, "직업": 2, "1단계Y/N": "Y", "2-1단계Y/N": "Y", "2-2단계Y/N": "N", "문장": "거의 공산당 같은 민주당이 또 정권을 잡으면 우리나라도 중국과 똑 같아질게다. KBS나 MBC가 언론이기를 포기한거 봐라. #@이름#이가 대통령 노릇하는 대한민국 땅에서도 언론환경이 땅바닥 아니더냐?", "대상하이라이트": "거의 공산당 같은 ''민주당'''이 또 정권을 잡으면 우리나라도 ''중국'''과 똑 같아질게다. ''KBS'''나 ''MBC'''가 언론이기를 포기한거 봐라. ''#@이름#'''이가 대통령 노릇하는 대한민국 땅에서도 언론환경이 땅바닥 아니더냐?", "인종/지역Y/N": "Y", "정치성향Y/N": "Y", "직업Y/N": "Y", "혐오 클래스": "Y", "특정 집단": "N", "그 외": "N"}