{"모욕": 1, "욕설": 1, "외설": 0, "폭력위협/범죄조장": 0, "성혐오": 0, "연령": 0, "인종/지역": 1, "장애": 0, "종교": 0, "정치성향": 0, "직업": 0, "1단계Y/N": "Y", "2-1단계Y/N": "N", "2-2단계Y/N": "Y", "문장": "아주 트랜스 일본인들 나셨어요. 우리 영토인 독도 반투먕하게 점찍어서 지도에 올리고 전범기인 욱일기 사용하게 하는건 정치적인 짓 아닌가? 왜 그건 입 꾹 ''쳐닫'''고 있다가 멀쩡한 #@이름# 어록 가지고 반일이니 ezr들이야? 그렇게 일본인 하고 싶으면 바다 건너가 ''토착왜구'''들아", "대상하이라이트": "아주 트랜스 일본인들 나셨어요. 우리 영토인 독도 반투먕하게 점찍어서 지도에 올리고 전범기인 욱일기 사용하게 하는건 정치적인 짓 아닌가? 왜 그건 입 꾹 쳐닫고 있다가 멀쩡한 #@이름# 어록 가지고 반일이니 ezr들이야? 그렇게 일본인 하고 싶으면 바다 건너가 토착왜구들아", "성혐오Y/N": "N", "연령Y/N": "N", "인종/지역Y/N": "Y", "장애Y/N": "N", "종교Y/N": "N", "정치성향Y/N": "N", "직업Y/N": "N", "혐오 클래스": "Y", "특정 집단": "N", "그 외": "N"}