{"모욕": 0, "욕설": 2, "외설": 0, "폭력위협/범죄조장": 0, "성혐오": 0, "연령": 0, "인종/지역": 0, "장애": 0, "종교": 0, "정치성향": 0, "직업": 0, "1단계Y/N": "Y", "2-1단계Y/N": "Y", "2-2단계Y/N": "Y", "문장": "야구는 부루조아들이 하는 놀이이다. 그래서 프로 야구가 있는 나라는 국민소득이 높은 나라다. 우리나라는 #@이름#이 국민의 눈과 귀를 가릴 목적으로 개발도상국일때 80년대 초반 도입했다. 국민소득이 겨우 만불도 안되었을때 불손한 목적으로 도입한 프로야구이다 보니 국민을 ''개, 돼지'''로 만들기에 적합했다. 썩은 프로야구 뿌리에 좋은 꽃이 피지 못하는건 당연하다. 이제 프로야구를 없애고 육상, 체조, 수영... 이런 사회체육 종목에 기업과 정부가 투자해야 할 시기이다.", "대상하이라이트": "야구는 부루조아들이 하는 놀이이다. 그래서 프로 야구가 있는 나라는 국민소득이 높은 나라다. 우리나라는 ''#@이름#'''이 국민의 눈과 귀를 가릴 목적으로 개발도상국일때 80년대 초반 도입했다. 국민소득이 겨우 만불도 안되었을때 불손한 목적으로 도입한 프로야구이다 보니 국민을 개, 돼지로 만들기에 적합했다. 썩은 프로야구 뿌리에 좋은 꽃이 피지 못하는건 당연하다. 이제 프로야구를 없애고 육상, 체조, 수영... 이런 사회체육 종목에 기업과 정부가 투자해야 할 시기이다.", "혐오 클래스": "N", "특정 집단": "N", "그 외": "Y"}