{"모욕": 2, "욕설": 1, "외설": 0, "폭력위협/범죄조장": 1, "성혐오": 0, "연령": 0, "인종/지역": 0, "장애": 0, "종교": 0, "정치성향": 0, "직업": 0, "1단계Y/N": "Y", "2-1단계Y/N": "Y", "2-2단계Y/N": "Y", "문장": "무능한 감독 #@이름#. 데리고 간 선수들 면면이 참 의심스럽다. 중심 타선이라는 놈들은 거의 삼진당하고, 감독은  투수교체 타임도 놓치고 져도 그렇게 ''개판'''으로 져야겠나. 메달을 못따도 죽기살기의 정신을 국민은 바라는데 니들은 뭐냐. 귀국하지마라 ''새끼'''들아.", "대상하이라이트": "''무능한 감독 #@이름#'''. 데리고 간 선수들 면면이 참 의심스럽다. 중심 타선이라는 놈들은 거의 삼진당하고, 감독은  투수교체 타임도 놓치고 져도 그렇게 개판으로 져야겠나. 메달을 못따도 죽기살기의 정신을 국민은 바라는데 니들은 뭐냐. 귀국하지마라 새끼들아.", "혐오 클래스": "N", "특정 집단": "N", "그 외": "Y"}