{"모욕": 1, "욕설": 0, "외설": 0, "폭력위협/범죄조장": 0, "성혐오": 0, "연령": 0, "인종/지역": 0, "장애": 0, "종교": 0, "정치성향": 0, "직업": 0, "1단계Y/N": "Y", "2-1단계Y/N": "Y", "2-2단계Y/N": "Y", "문장": "프로야구 중단이유가 올림픽 병역특혜 아닌가 #@이름# 등 등에 책임전가 애초부터 동메달은 따놓은 당상이니 제사보다는 젯밥에 관심이 있어서 아닌가 펄펄나는 #@이름# 그래도 #@이름# 선수가 얼마나 많았나 병역특혜 주려고 kbo학연지연으로엮여 외국에서 아무리 야구를 잘하고 돌아온들 ''왕따''' 더운날씨에 선수여러분들 수고하셨습니다 세계적인 축구선수 #@이름# 한국축구협회 자리하나 없는 고질적인 한국의 체육계", "대상하이라이트": "프로야구 중단이유가 올림픽 병역특혜 아닌가 #@이름# 등 등에 책임전가 애초부터 동메달은 따놓은 당상이니 제사보다는 젯밥에 관심이 있어서 아닌가 펄펄나는 #@이름# 그래도 #@이름# 선수가 얼마나 많았나 병역특혜 주려고 kbo학연지연으로엮여 외국에서 아무리 야구를 잘하고 돌아온들 왕따 더운날씨에 선수여러분들 수고하셨습니다 세계적인 축구선수 #@이름# 한국축구협회 자리하나 없는 고질적인 ''한국의 체육계'''", "혐오 클래스": "N", "특정 집단": "Y", "그 외": "N"}