{"모욕": 2, "욕설": 0, "외설": 0, "폭력위협/범죄조장": 0, "성혐오": 0, "연령": 0, "인종/지역": 0, "장애": 0, "종교": 0, "정치성향": 3, "직업": 0, "1단계Y/N": "Y", "2-1단계Y/N": "Y", "2-2단계Y/N": "Y", "문장": "진짜 스가랑 비교되네 이 ''무능'''한 인간아 ''큰소리'''나 ''뻥뻥''' 칠줄 알지 국정을 운영하는 인간이 언제나 최악을 생각하지 않고 아무 근거없이 좋은 쪽으로만 생각하다가 상황이 바뀌면 ''허둥지둥''' 국민들은 나몰라라 ''내팽개치'''고 얼마나 급했으면 #@이름#까지 풀어주면서 백신 구해오라고 시켰을까 ㅋㅋ ''답'''도 ''없'''는 ''개''' ''무능'''한 인간 ''깜빵''' 갈 준비나 해라", "대상하이라이트": "진짜 스가랑 비교되네 이 무능한 ''인간'''아 큰소리나 뻥뻥 칠줄 알지 국정을 운영하는 인간이 언제나 최악을 생각하지 않고 아무 근거없이 좋은 쪽으로만 생각하다가 상황이 바뀌면 허둥지둥 국민들은 나몰라라 내팽개치고 얼마나 급했으면 #@이름#까지 풀어주면서 백신 구해오라고 시켰을까 ㅋㅋ 답도 없는 개 무능한 ''인간''' 깜빵 갈 준비나 해라", "정치성향Y/N": "Y", "혐오 클래스": "Y", "특정 집단": "N", "그 외": "N"}