{"모욕": 1, "욕설": 1, "외설": 0, "폭력위협/범죄조장": 0, "성혐오": 0, "연령": 0, "인종/지역": 0, "장애": 0, "종교": 0, "정치성향": 2, "직업": 0, "1단계Y/N": "Y", "2-1단계Y/N": "Y", "2-2단계Y/N": "Y", "문장": "나는 이놈의 정권의 무리들이 전부 ''대갈통'''이 안돌아간다는 것을 알고 있다 코로나에 걸리기 쉽고 급속도로 번져가는 부류가 20~30대가 아니더냐.,. 걔네들은 순서가 뒤로 밀리고 나이드신 노인네들먼저 접종을 했으니 이런 사단이 난것은 아닌가?OOO들 ,, 이건 결과가 뻔했던 것이었다~~~~~~~~", "대상하이라이트": "나는 이놈의 ''정권'''의 무리들이 전부 대갈통이 안돌아간다는 것을 알고 있다 코로나에 걸리기 쉽고 급속도로 번져가는 부류가 20~30대가 아니더냐.,. 걔네들은 순서가 뒤로 밀리고 나이드신 노인네들먼저 접종을 했으니 이런 사단이 난것은 아닌가?OOO들 ,, 이건 결과가 뻔했던 것이었다~~~~~~~~", "정치성향Y/N": "Y", "혐오 클래스": "Y", "특정 집단": "N", "그 외": "N"}