{"모욕": 3, "욕설": 2, "외설": 1, "폭력위협/범죄조장": 0, "성혐오": 0, "연령": 1, "인종/지역": 0, "장애": 0, "종교": 0, "정치성향": 2, "직업": 0, "1단계Y/N": "Y", "2-1단계Y/N": "N", "2-2단계Y/N": "Y", "문장": "멋있어 보일려고 고개 져치면서 머리 뒤로 쓰다듬는다는 연출 전문가께서 이번에는 차라리 ''누드를 보여 주는''' 연출을 했으면 대깨조들이 비명을 지르며. 좋아 했을텐데.!세상에 나이 ''쳐먹고도''' 저러고 싶은가.? ''관종'''도 저런 관종이면 ''정신병 말기수준''' 아닌가.?마누라는 감옥에 있는데 부끄럽지도 않은지.? ''모자란건가'''.? ''쑈를''' 하는건가.? 보는 사람들이 민망해서 얼굴 벌개 지겠네.!''ㅉㅉㅉ'''", "대상하이라이트": "멋있어 보일려고 고개 져치면서 머리 뒤로 쓰다듬는다는 연출 전문가께서 이번에는 차라리 누드를 보여 주는 연출을 했으면 대깨조들이 비명을 지르며. 좋아 했을텐데.!세상에 나이 쳐먹고도 저러고 싶은가.? 관종도 저런 관종이면 정신병 말기수준 아닌가.?마누라는 감옥에 있는데 부끄럽지도 않은지.? 모자란건가.? 쑈를 하는건가.? 보는 사람들이 민망해서 얼굴 벌개 지겠네.!ㅉㅉㅉ", "성혐오Y/N": "N", "연령Y/N": "Y", "인종/지역Y/N": "N", "장애Y/N": "N", "종교Y/N": "N", "정치성향Y/N": "Y", "직업Y/N": "N", "혐오 클래스": "N", "특정 집단": "N", "그 외": "N"}