{"모욕": 1, "욕설": 0, "외설": 0, "폭력위협/범죄조장": 0, "성혐오": 0, "연령": 0, "인종/지역": 0, "장애": 0, "종교": 0, "정치성향": 0, "직업": 0, "1단계Y/N": "Y", "2-1단계Y/N": "Y", "2-2단계Y/N": "Y", "문장": "세계에서 출산율 제일 낮은 나라에서 영유아, 미성년자있는 가정보다 유교국가랍시고 백신도 노인네들부터! 뭐든지 장유유서. 전국민 재난지원금 필요없고 세금감면이나 좀 해주던가, 웃돈 주고라도 백신 좀 구해오든가 진짜 나라가 능력이 없어. 선진국이다 ''개소리'''나 실실대고", "대상하이라이트": "세계에서 출산율 제일 낮은 ''나라'''에서 영유아, 미성년자있는 가정보다 유교국가랍시고 백신도 노인네들부터! 뭐든지 장유유서. 전국민 재난지원금 필요없고 세금감면이나 좀 해주던가, 웃돈 주고라도 백신 좀 구해오든가 진짜 ''나라'''가 능력이 없어. 선진국이다 개소리나 실실대고", "혐오 클래스": "N", "특정 집단": "N", "그 외": "Y"}