{"모욕": 2, "욕설": 0, "외설": 0, "폭력위협/범죄조장": 0, "성혐오": 0, "연령": 0, "인종/지역": 0, "장애": 0, "종교": 0, "정치성향": 1, "직업": 0, "1단계Y/N": "Y", "2-1단계Y/N": "Y", "2-2단계Y/N": "Y", "문장": "또 또 또 싸움 붙인다ㅋㅋ 수도권VS지방 싸움 붙이는 것도 서로 감시하고 싸워야 비난의 화살을 정부 말고 서로에게 돌리게 하니까. ''공산''' 정부는 인간관계 다 찢고, 빈부격차 벌리고, 재미 보는 중인데ㅋㅋㅋ''개'''''돼지''' 너만자영업자네 니가밖에나갔네 #@이름#을찍었네 걍 서로 물고뜯고 지들끼리 욕하기 바쁨. ''머리'''가 ''안 좋'''긴 해.", "대상하이라이트": "또 또 또 싸움 붙인다ㅋㅋ 수도권VS지방 싸움 붙이는 것도 서로 감시하고 싸워야 비난의 화살을 ''정부''' 말고 서로에게 돌리게 하니까. 공산 ''정부'''는 인간관계 다 찢고, 빈부격차 벌리고, 재미 보는 중인데ㅋㅋㅋ개돼지 너만자영업자네 니가밖에나갔네 #@이름#을찍었네 걍 서로 물고뜯고 지들끼리 욕하기 바쁨. 머리가 안 좋긴 해.", "정치성향Y/N": "Y", "혐오 클래스": "Y", "특정 집단": "N", "그 외": "Y"}