{"모욕": 1, "욕설": 2, "외설": 0, "폭력위협/범죄조장": 0, "성혐오": 0, "연령": 0, "인종/지역": 0, "장애": 0, "종교": 0, "정치성향": 1, "직업": 0, "1단계Y/N": "Y", "2-1단계Y/N": "Y", "2-2단계Y/N": "Y", "문장": "#@이름# 검사장이 #@이름#씨 라고 지칭한거 매우 잘 한일이요 언론에서도 #@이름# 전 장관이 아닌 #@이름# 또는 #@이름#씨 라고 써주면 그 언론사 고맙게 여길 것이요 장관역할을 한게 있어야 대우를 해주고 받는건데 그여자는 한거라곤 윤총장 물고 늘어지는거 외엔 무얼했나 이젠 꺼져서 없어져라 ''추접'''한 ''×''',", "대상하이라이트": "#@이름# 검사장이 ''#@이름#'''씨 라고 지칭한거 매우 잘 한일이요 언론에서도 ''#@이름#''' 전 ''장관'''이 아닌 ''#@이름#''' 또는 ''#@이름#'''씨 라고 써주면 그 언론사 고맙게 여길 것이요 ''장관'''역할을 한게 있어야 대우를 해주고 받는건데 그''여자'''는 한거라곤 윤총장 물고 늘어지는거 외엔 무얼했나 이젠 ''꺼져'''서 없어져라 추접한 ×,", "정치성향Y/N": "Y", "혐오 클래스": "Y", "특정 집단": "N", "그 외": "N"}