{"모욕": 2, "욕설": 0, "외설": 0, "폭력위협/범죄조장": 0, "성혐오": 0, "연령": 0, "인종/지역": 0, "장애": 0, "종교": 0, "정치성향": 0, "직업": 0, "1단계Y/N": "Y", "2-1단계Y/N": "Y", "2-2단계Y/N": "Y", "문장": "아니 너무 어이가없네. 독감백신도 맞으면 독감 안걸리는게 아니라 크게 아플거 덜아프게 하는 정도인데. 무슨 코로나 백신맞으면 코로나에 안걸릴거라 생각하는 사람들 너무 ''바보'''같은거 아닌가? 백신 맞아도 마스크쓰고 거리두기하고 관리를 계속 잘해야지ㅡㅡ", "대상하이라이트": "아니 너무 어이가없네. 독감백신도 맞으면 독감 안걸리는게 아니라 크게 아플거 덜아프게 하는 정도인데. 무슨 ''코로나 백신맞으면 코로나에 안걸릴거라 생각하는 사람'''들 너무 바보같은거 아닌가? 백신 맞아도 마스크쓰고 거리두기하고 관리를 계속 잘해야지ㅡㅡ", "혐오 클래스": "N", "특정 집단": "Y", "그 외": "N"}