{"모욕": 2, "욕설": 1, "외설": 0, "폭력위협/범죄조장": 0, "성혐오": 0, "연령": 0, "인종/지역": 0, "장애": 0, "종교": 0, "정치성향": 2, "직업": 0, "1단계Y/N": "Y", "2-1단계Y/N": "Y", "2-2단계Y/N": "Y", "문장": "창작자가 ''빨갱이'''던가 위에서시킨 ''놈'''이 ''빨갱이'''던가~~~#@이름#가 민간 ''학살'''자냐?? #@이름#이가 민간 ''학살'''자냐???고만좀 해라 진짜~~~니들 기준에서는 #@이름#가 원수겠지~~~조선민주주의 인민공화국을 둘로 갈라 놓은 원수\n", "대상하이라이트": "''창작자'''가 ''빨갱이'''던가 ''위에서시킨 놈'''이 ''빨갱이'''던가~~~''#@이름#'''가 ''민간 학살자'''냐?? ''#@이름#'''이가 ''민간 학살자'''냐???고만좀 해라 진짜~~~니들 기준에서는 ''#@이름#'''가 원수겠지~~~조선민주주의 인민공화국을 둘로 갈라 놓은 원수\n", "정치성향Y/N": "Y", "혐오 클래스": "Y", "특정 집단": "N", "그 외": "Y"}