{"모욕": 1, "욕설": 0, "외설": 0, "폭력위협/범죄조장": 0, "성혐오": 0, "연령": 0, "인종/지역": 2, "장애": 0, "종교": 0, "정치성향": 2, "직업": 0, "1단계Y/N": "Y", "2-1단계Y/N": "Y", "2-2단계Y/N": "Y", "문장": "''친일''' 논란이 한 두번 아닌데 본인이 ''친일'''이 아니라고 부정도 안 하니 벌써부터 목숨을 꾾니 분란을 만드는데 분명 이 자는 ''구김당'''인데 이 자가 민주당 대선주자 #@이름#가 왜 거기서 나와 뭐 #@이름#의 ''포카페이스'''라고\n", "대상하이라이트": "친일 논란이 한 두번 아닌데 본인이 친일이 아니라고 부정도 안 하니 벌써부터 목숨을 꾾니 분란을 만드는데 분명 이 자는 구김당인데 이 자가 민주당 대선주자 #@이름#가 왜 거기서 나와 뭐 #@이름#의 포카페이스라고\n", "인종/지역Y/N": "Y", "정치성향Y/N": "Y", "혐오 클래스": "Y", "특정 집단": "N", "그 외": "N"}