{"모욕": 1, "욕설": 1, "외설": 0, "폭력위협/범죄조장": 0, "성혐오": 0, "연령": 0, "인종/지역": 1, "장애": 0, "종교": 0, "정치성향": 0, "직업": 0, "1단계Y/N": "Y", "2-1단계Y/N": "Y", "2-2단계Y/N": "Y", "문장": "이게 군대냐 아프카니스탄 정부군 수준 아니냐? 국방부장관 이넘은 왜 옷 안벗냐? 고향인 광주로 나향해라 비겁한''넘''' 명색이 근 출신이면 책임지고 물러나야지 #@이름# 비슷한 인간 같은 동향이라도 #@이름#,#@이름# 하곤 180도 다르네 지금 북이 밀고 내려오면 다 탈영 할것 같다 하기야 국군통수권자가 #@이름#으르 의심 되는 상황이니 말 할것 있냐", "대상하이라이트": "이게 ''군대'''냐 아프카니스탄 정부군 수준 아니냐? 국방부장관 이넘은 왜 옷 안벗냐? 고향인 광주로 나향해라 비겁한넘 명색이 근 출신이면 책임지고 물러나야지 #@이름# 비슷한 인간 같은 동향이라도 #@이름#,#@이름# 하곤 180도 다르네 지금 북이 밀고 내려오면 다 탈영 할것 같다 하기야 국군통수권자가 #@이름#으르 의심 되는 상황이니 말 할것 있냐", "인종/지역Y/N": "Y", "혐오 클래스": "Y", "특정 집단": "N", "그 외": "N"}