{"모욕": 1, "욕설": 0, "외설": 0, "폭력위협/범죄조장": 0, "성혐오": 0, "연령": 0, "인종/지역": 0, "장애": 0, "종교": 0, "정치성향": 1, "직업": 0, "1단계Y/N": "Y", "2-1단계Y/N": "Y", "2-2단계Y/N": "Y", "문장": "여기가 자유대한민국 맞나요?지금도 세계에서 유일하게 취등록세, 보유세, 양도세 중과(82.5)로 최고 수준인데요. 종부세는 우리나라만 있죠.여기에다 또 규제를 한다니 정신 나간 사람들이네요. 역시 민주당은 공산당 마인드입니다. 지지하는 세력들 후원 많이 하던데 인간관계시 민주당 지지하는 사람들과는 손절해야겠습니다.", "대상하이라이트": "여기가 자유대한민국 맞나요?지금도 세계에서 유일하게 취등록세, 보유세, 양도세 중과(82.5)로 최고 수준인데요. 종부세는 우리나라만 있죠.여기에다 또 규제를 한다니 정신 나간 사람들이네요. 역시 ''민주당'''은 공산당 마인드입니다. 지지하는 세력들 후원 많이 하던데 인간관계시 ''민주당 지지하는 사람'''들과는 손절해야겠습니다.", "정치성향Y/N": "Y", "혐오 클래스": "Y", "특정 집단": "Y", "그 외": "N"}