{"모욕": 1, "욕설": 0, "외설": 0, "폭력위협/범죄조장": 0, "성혐오": 0, "연령": 0, "인종/지역": 0, "장애": 0, "종교": 0, "정치성향": 0, "직업": 0, "1단계Y/N": "Y", "2-1단계Y/N": "Y", "2-2단계Y/N": "Y", "문장": "난 보수가 집권해도 괜찮다고 생각하는 사람이다 하지만 #@이름#는 아닌것 같다 상식과 공정을 애기하는 사람이 한국사회의 상식에는 ''깡통'''이고, 모르면 배우면 되지만 입만 열면 ''실언'''을 연발한다 또한 사고는 극우인데 말로는 중도와 진보까지 말한다 중도와 진보의 사람들은 국힘과 반#@이름#이면 지지하는 것이 아니라 제대로 된 정치철학과 비전이 있어야 지지한다 왜? 중도와 진보쪽 사람들이 #@이름#와 #@이름#을 지지하는지 곰곰히 생각해봐라 #@이름#는 대통령감이 아니다 ㅎㅎㅎ", "대상하이라이트": "난 보수가 집권해도 괜찮다고 생각하는 사람이다 하지만 ''#@이름#'''는 아닌것 같다 상식과 공정을 애기하는 사람이 한국사회의 상식에는 깡통이고, 모르면 배우면 되지만 입만 열면 실언을 연발한다 또한 사고는 극우인데 말로는 중도와 진보까지 말한다 중도와 진보의 사람들은 국힘과 반#@이름#이면 지지하는 것이 아니라 제대로 된 정치철학과 비전이 있어야 지지한다 왜? 중도와 진보쪽 사람들이 #@이름#와 #@이름#을 지지하는지 곰곰히 생각해봐라 ''#@이름#'''는 대통령감이 아니다 ㅎㅎㅎ", "혐오 클래스": "N", "특정 집단": "N", "그 외": "Y"}