{"모욕": 1, "욕설": 0, "외설": 0, "폭력위협/범죄조장": 0, "성혐오": 0, "연령": 0, "인종/지역": 0, "장애": 0, "종교": 0, "정치성향": 0, "직업": 1, "1단계Y/N": "Y", "2-1단계Y/N": "Y", "2-2단계Y/N": "Y", "문장": "#@이름#씨.당신 법관 맞냐? 국민의 정서는 죄를 지었으면 죄값을 받는겁니다. 그리고 아버지가 부당한 방법으로 딸에게 도움을 줬다면 당연히 법은 딸에게 주어진 부당한 이익을 환수하는게 당연한겁니다. 그럼 부당하게 준 아버지는 처벌 받고 그 혜택을 본 딸에게는 그 혜택도 그냥 둬야 된다는 말인가요? 그리고 정확히 말해서 딸을 기소한적이 있었는가요? 없었잖아요...#@이름#씨 거 주디 ''함부러 놀리는'''거 아닙니다.", "대상하이라이트": "''#@이름#'''씨.당신 법관 맞냐? 국민의 정서는 죄를 지었으면 죄값을 받는겁니다. 그리고 아버지가 부당한 방법으로 딸에게 도움을 줬다면 당연히 법은 딸에게 주어진 부당한 이익을 환수하는게 당연한겁니다. 그럼 부당하게 준 아버지는 처벌 받고 그 혜택을 본 딸에게는 그 혜택도 그냥 둬야 된다는 말인가요? 그리고 정확히 말해서 딸을 기소한적이 있었는가요? 없었잖아요...''#@이름#'''씨 거 주디 함부러 놀리는거 아닙니다.", "직업Y/N": "Y", "혐오 클래스": "Y", "특정 집단": "N", "그 외": "N"}