{"모욕": 2, "욕설": 3, "외설": 0, "폭력위협/범죄조장": 0, "성혐오": 0, "연령": 0, "인종/지역": 0, "장애": 0, "종교": 0, "정치성향": 2, "직업": 0, "1단계Y/N": "Y", "2-1단계Y/N": "Y", "2-2단계Y/N": "Y", "문장": "그냥 놔두시오! 술이라도 안 먹으면 무슨 정신으로 살겠쏘! 말만 꺼내면 ''무식'''이 탄로나 구설에 오르고 장모에 마누라에 얼마나 스트레스 받겠어! ''국민의짐''' ''패거리'''에 합류했지만 지 세력이 있나? 토사구팽 당할까봐 노심초사... 맨날 술이지! 저 사람이 조직에 충성하는 인간인데 오죽하면 조직의 우두머리를 깜빵에 ''쳐''' 넣었는데도 살겠다고 들어갔겠어!", "대상하이라이트": "그냥 놔두시오! 술이라도 안 먹으면 무슨 정신으로 살겠쏘! 말만 꺼내면 무식이 탄로나 구설에 오르고 장모에 마누라에 얼마나 스트레스 받겠어! ''국민의짐''' 패거리에 합류했지만 지 세력이 있나? 토사구팽 당할까봐 노심초사... 맨날 술이지! 저 사람이 조직에 충성하는 인간인데 오죽하면 ''조직의 우두머리'''를 깜빵에 쳐 넣었는데도 살겠다고 들어갔겠어!", "정치성향Y/N": "Y", "혐오 클래스": "Y", "특정 집단": "N", "그 외": "Y"}