{"모욕": 2, "욕설": 1, "외설": 0, "폭력위협/범죄조장": 0, "성혐오": 0, "연령": 0, "인종/지역": 0, "장애": 0, "종교": 0, "정치성향": 2, "직업": 0, "1단계Y/N": "Y", "2-1단계Y/N": "Y", "2-2단계Y/N": "Y", "문장": "팩트는 #@이름# 저 인간 과거에 친일 발언해서 방송국에서도 하차한 ''놈'''임! 그 이후로 민주당에 붙어서 ''대깨문 짓'''하면서 정치판에 기웃거림!저런 ''놈'''한테 한 자리 내준#@이름#도 정상은 아니란 소리..유유상종!쯧쯧", "대상하이라이트": "팩트는 ''#@이름#''' 저 인간 과거에 친일 발언해서 방송국에서도 하차한 놈임! 그 이후로 민주당에 붙어서 대깨문 짓하면서 정치판에 기웃거림!저런 놈한테 한 자리 내준''#@이름#'''도 정상은 아니란 소리..유유상종!쯧쯧", "정치성향Y/N": "Y", "혐오 클래스": "Y", "특정 집단": "N", "그 외": "N"}