{"모욕": 2, "욕설": 0, "외설": 0, "폭력위협/범죄조장": 0, "성혐오": 0, "연령": 0, "인종/지역": 0, "장애": 0, "종교": 0, "정치성향": 1, "직업": 1, "1단계Y/N": "Y", "2-1단계Y/N": "Y", "2-2단계Y/N": "N", "문장": "공정하고 거리가 먼 KBS 정권 입맞에맞춰서 편파보도 그 뿐만이아니라 거짓보도만 하는 KBS / 그렇게 #@이름#떄는 온갖풍자와 해악질 그리고 나체사진 및 정치개그에 앞장섰던 분들이 현정권의 내로남불과 온갖 거짓정보를 퍼트리는 이상황에서는 누구하나 나서는 자가없음. 그러니 개콘이 망하는건 당연지사. 그쪽사람을 지지하고 그쪽당을 지지하고, 반대되는사람이있으면 철저하게 배제되는 기이한현상. 블랙리스트? 문화계 블랙리스트는 당연한거였다 이렇게 블랙리스트없이 철저하게 반가르기하는건 그쪽이 더잘하니까 그리고 씨를 잘라야지 역시 내로남불정권", "대상하이라이트": "공정하고 거리가 먼 ''KBS''' ''정권''' 입맞에맞춰서 편파보도 그 뿐만이아니라 거짓보도만 하는 ''KBS''' / 그렇게 #@이름#떄는 온갖풍자와 해악질 그리고 나체사진 및 정치개그에 앞장섰던 분들이 ''현정권'''의 내로남불과 온갖 거짓정보를 퍼트리는 이상황에서는 누구하나 나서는 자가없음. 그러니 개콘이 망하는건 당연지사. 그쪽사람을 지지하고 그쪽당을 지지하고, 반대되는사람이있으면 철저하게 배제되는 기이한현상. 블랙리스트? 문화계 블랙리스트는 당연한거였다 이렇게 블랙리스트없이 철저하게 반가르기하는건 그쪽이 더잘하니까 그리고 씨를 잘라야지 역시 내로남불''정권'''", "정치성향Y/N": "Y", "직업Y/N": "Y", "혐오 클래스": "Y", "특정 집단": "N", "그 외": "N"}