{"모욕": 1, "욕설": 0, "외설": 0, "폭력위협/범죄조장": 0, "성혐오": 0, "연령": 0, "인종/지역": 0, "장애": 0, "종교": 0, "정치성향": 1, "직업": 0, "1단계Y/N": "Y", "2-1단계Y/N": "Y", "2-2단계Y/N": "Y", "문장": "그래서 가정교육이 중요하고 어린시절 환경이 중하고 본성은 변하지안는다 그래서 극한상항이되면 본서미나온다 형.형수에게 ''쌍욕하'''는거보면 알수있다 가족간의 감정조절도 못하는위인이 무슨나라을 다스린다고 여기서 고만하고 남은인생 집안이나잘다스리세요..집구석이편해야 모든게편하니까", "대상하이라이트": "그래서 가정교육이 중요하고 어린시절 환경이 중하고 본성은 변하지안는다 그래서 극한상항이되면 본서미나온다 형.형수에게 쌍욕하는거보면 알수있다 ''가족간의 감정조절도 못하는위인'''이 무슨나라을 다스린다고 여기서 고만하고 남은인생 집안이나잘다스리세요..집구석이편해야 모든게편하니까", "정치성향Y/N": "Y", "혐오 클래스": "Y", "특정 집단": "N", "그 외": "N"}