{"모욕": 1, "욕설": 0, "외설": 0, "폭력위협/범죄조장": 0, "성혐오": 0, "연령": 0, "인종/지역": 0, "장애": 0, "종교": 1, "정치성향": 0, "직업": 0, "1단계Y/N": "Y", "2-1단계Y/N": "Y", "2-2단계Y/N": "Y", "문장": "\n신천지 교인하고 그들의 영생에 관해 논리적으로 대화해 본적 있으심? 기회되면 얘기해보삼.정말 이들은 일반적인 상식으로는 교화가 어렵겠구나 뼈저리게 느끼게 됨.어느순간 그들의 ''뇌구조'''와 신념, 행동들이 서서히 공포로 느껴지게됨요.직접 안겪어본 사람은 이해가 어려울거임요.그리고 그들도 일반인들과 섞여있으면 아무도 모르게 평범하다는게 또 무섭죠.내가 왜 이 설명을 드리냐면 지금 좌파정권을 지지하는 좌파강경파와 일부 지지자들이 제가 앞서 설명한 신천지 교인들과 따르는 신념과 이념이 다를 뿐이지 그 강령들과 집단적행태,알고리즘이 일치한다는것.", "대상하이라이트": "\n''신천지 교인'''하고 그들의 영생에 관해 논리적으로 대화해 본적 있으심? 기회되면 얘기해보삼.정말 이들은 일반적인 상식으로는 교화가 어렵겠구나 뼈저리게 느끼게 됨.어느순간 그들의 뇌구조와 신념, 행동들이 서서히 공포로 느껴지게됨요.직접 안겪어본 사람은 이해가 어려울거임요.그리고 그들도 일반인들과 섞여있으면 아무도 모르게 평범하다는게 또 무섭죠.내가 왜 이 설명을 드리냐면 지금 좌파정권을 지지하는 좌파강경파와 일부 지지자들이 제가 앞서 설명한 신천지 교인들과 따르는 신념과 이념이 다를 뿐이지 그 강령들과 집단적행태,알고리즘이 일치한다는것.", "종교Y/N": "Y", "혐오 클래스": "Y", "특정 집단": "N", "그 외": "N"}