{"모욕": 2, "욕설": 2, "외설": 0, "폭력위협/범죄조장": 0, "성혐오": 0, "연령": 0, "인종/지역": 0, "장애": 0, "종교": 0, "정치성향": 2, "직업": 0, "1단계Y/N": "Y", "2-1단계Y/N": "N", "2-2단계Y/N": "Y", "문장": "''존나'''선진국..선진국... 하더니 이런''꼴''' 당하려고 ''ㅈㄹ발광''' 한거냐? 그냥 개도국에 만족이나 하지 뭔 ''개'''쪽이야 그렇다고 중국을 막기라도 할거냐 뭐할거냐? 중국에 찍소리도 못하면서 ''ㄷㅅ'''아 창피당하라고 너깟''놈'''을 대통령에 뽑아준줄 아냐? 그냥 하야해라 넌 #@이름#보다도 못한''넘'''이다", "대상하이라이트": "존나 선진국..선진국... 하더니 이런꼴 당하려고 ㅈㄹ발광 한거냐? 그냥 개도국에 만족이나 하지 뭔 개쪽이야 그렇다고 중국을 막기라도 할거냐 뭐할거냐? 중국에 찍소리도 못하면서 ㄷㅅ아 창피당하라고 너깟놈을 대통령에 뽑아준줄 아냐? 그냥 하야해라 넌 #@이름#보다도 못한넘이다", "성혐오Y/N": "N", "연령Y/N": "N", "인종/지역Y/N": "N", "장애Y/N": "N", "종교Y/N": "N", "정치성향Y/N": "Y", "직업Y/N": "N", "혐오 클래스": "Y", "특정 집단": "N", "그 외": "N"}