{"모욕": 2, "욕설": 0, "외설": 0, "폭력위협/범죄조장": 0, "성혐오": 0, "연령": 0, "인종/지역": 0, "장애": 0, "종교": 0, "정치성향": 0, "직업": 0, "1단계Y/N": "Y", "2-1단계Y/N": "Y", "2-2단계Y/N": "Y", "문장": "\n저 선수가 페미인지 아닌지 거기에 상관없이, 일단 국위선양을 한 금메달리스트인데 응원과 격려는 못할망정, 박탈이니 끌어내리니 뭐니 하며 키보드 앞에서 발광이나 하고 있는 꼬라지들이 가관이다, 거기에 안산선수를 강제로 페미영웅으로 만들어서 남혐을 정당화하고 있는 ''꼴'''''페미'''들도 한트럭에, 이걸 정치프레임으로 이용해먹는 정의없는 정의당까지.. 참 아름다운 콜라보에요~", "대상하이라이트": "\n저 선수가 페미인지 아닌지 거기에 상관없이, 일단 국위선양을 한 금메달리스트인데 응원과 격려는 못할망정, 박탈이니 끌어내리니 뭐니 하며 키보드 앞에서 발광이나 하고 있는 꼬라지들이 가관이다, 거기에 안산선수를 강제로 페미영웅으로 만들어서 남혐을 정당화하고 있는 ''꼴페미'''들도 한트럭에, 이걸 정치프레임으로 이용해먹는 정의없는 정의당까지.. 참 아름다운 콜라보에요~", "혐오 클래스": "N", "특정 집단": "Y", "그 외": "N"}