{"모욕": 2, "욕설": 3, "외설": 0, "폭력위협/범죄조장": 0, "성혐오": 0, "연령": 0, "인종/지역": 3, "장애": 0, "종교": 0, "정치성향": 2, "직업": 0, "1단계Y/N": "Y", "2-1단계Y/N": "Y", "2-2단계Y/N": "Y", "문장": "''항국''' 외교부ㆍ정말 이해안되네?''짱깨'''ㆍ''쭝공''' 대사는 왜 가만두는거야?속국근성들이 뼈에 박혀있구먼?#@이름#은 퇴임후 ''찐삥'''이 전속 ''내시'''로 자금성에 입궐해라?멋찌다ㆍ''항국'''", "대상하이라이트": "항국 ''외교부'''ㆍ정말 이해안되네?''짱깨'''ㆍ''쭝공''' ''대사'''는 왜 가만두는거야?속국근성들이 뼈에 박혀있구먼?''#@이름#'''은 퇴임후 ''찐삥'''이 전속 내시로 자금성에 입궐해라?멋찌다ㆍ''항국'''", "인종/지역Y/N": "Y", "정치성향Y/N": "Y", "혐오 클래스": "Y", "특정 집단": "N", "그 외": "Y"}