{"모욕": 1, "욕설": 2, "외설": 1, "폭력위협/범죄조장": 0, "성혐오": 2, "연령": 0, "인종/지역": 0, "장애": 0, "종교": 0, "정치성향": 0, "직업": 1, "1단계Y/N": "Y", "2-1단계Y/N": "Y", "2-2단계Y/N": "Y", "문장": "''이상'''한 남초 말 들어준 ????의혹때부터 그냥 ''망했'''었음 세계공통적으로 작다라는 의미로만 사용하는거고 페미들은 ''남자'''''고추'''라고 생각안하는데 괜히 ''이상'''한 남초에서 난리 근데 기자들은 그걸 또 기사로 써주고 ''얼탱'''이가 없지", "대상하이라이트": "이상한 ''남초''' 말 들어준 ????의혹때부터 그냥 망했었음 세계공통적으로 작다라는 의미로만 사용하는거고 페미들은 남자고추라고 생각안하는데 괜히 이상한 ''남초'''에서 난리 근데 ''기자'''들은 그걸 또 기사로 써주고 얼탱이가 없지", "성혐오Y/N": "Y", "직업Y/N": "Y", "혐오 클래스": "Y", "특정 집단": "Y", "그 외": "N"}