{"모욕": 2, "욕설": 0, "외설": 0, "폭력위협/범죄조장": 0, "성혐오": 0, "연령": 0, "인종/지역": 0, "장애": 0, "종교": 0, "정치성향": 0, "직업": 0, "1단계Y/N": "Y", "2-1단계Y/N": "Y", "2-2단계Y/N": "Y", "문장": "''문재앙'''과 방역 전문가라는 인간들이 거리두기나 하고 국민들 통제나 하려고 했지 정작 중요한 백신 접종에 대해서는 대비책도 없었고 ''무지했'''다. 백신 개발도 선진국에 비하면 많이 뒤쳐졌고 이런 ''비정상적'''인 상황이 지속된다면 서민 경제도 걱정이다.", "대상하이라이트": "''문재앙'''과 ''방역 전문가라는 인간'''들이 거리두기나 하고 국민들 통제나 하려고 했지 정작 중요한 백신 접종에 대해서는 대비책도 없었고 무지했다. 백신 개발도 선진국에 비하면 많이 뒤쳐졌고 이런 비정상적인 상황이 지속된다면 서민 경제도 걱정이다.", "혐오 클래스": "N", "특정 집단": "Y", "그 외": "Y"}