{"모욕": 3, "욕설": 3, "외설": 1, "폭력위협/범죄조장": 0, "성혐오": 2, "연령": 0, "인종/지역": 1, "장애": 0, "종교": 0, "정치성향": 0, "직업": 0, "1단계Y/N": "Y", "2-1단계Y/N": "Y", "2-2단계Y/N": "Y", "문장": "한국보다 여성인권 높은 중국에서 저런일이 일어난다네. 팔자편한 ''개한민국''' ''쉽잡치뇬'''들, 저기가서 여자라서 당했다, 동일임금 동일노동, 유리천장, ''쭝남''' 외쳐봐라. 바로 니들 인체의신비에 박제로 보내질꺼다. ㅋㅋ ''개''' ''쉽잡치뇬'''들 ㅋ", "대상하이라이트": "한국보다 여성인권 높은 중국에서 저런일이 일어난다네. 팔자편한 ''개한민국 쉽잡치뇬'''들, 저기가서 여자라서 당했다, 동일임금 동일노동, 유리천장, 쭝남 외쳐봐라. 바로 니들 인체의신비에 박제로 보내질꺼다. ㅋㅋ ''개 쉽잡치뇬'''들 ㅋ", "성혐오Y/N": "Y", "인종/지역Y/N": "Y", "혐오 클래스": "Y", "특정 집단": "N", "그 외": "N"}