{"모욕": 2, "욕설": 0, "외설": 0, "폭력위협/범죄조장": 0, "성혐오": 0, "연령": 0, "인종/지역": 1, "장애": 0, "종교": 0, "정치성향": 2, "직업": 0, "1단계Y/N": "Y", "2-1단계Y/N": "Y", "2-2단계Y/N": "Y", "문장": "원자력기구가 안전하다고 인정하고 미국이 자국조사단 파견해서 안전하다고 인정햇고 한국이 wto에 국제재판하면서 끝내 후쿠시마산 농수산물에 방사능 위험성 입증못햇고 수많은 논문들이 뒷받침하는데 방사능이랑 방사선이 뭐가 다른지도 모르는 한국 ''대깨문'''들만 후쿠시마 방사능 거림 ㅋㅋㅋ 니들은 후쿠시마 방사능이 그렇게 위험하면 그동네랑 같은 해류타고 겨우 수백키로 떨어진 한반도에서 어떻게 밥먹고 사냐? ㅋㅋㅋ 후쿠시마에서 피폭되서 사망한사람 한명이라도 본사람??? ㅋㅋㅋㅋ\n", "대상하이라이트": "원자력기구가 안전하다고 인정하고 미국이 자국조사단 파견해서 안전하다고 인정햇고 한국이 wto에 국제재판하면서 끝내 후쿠시마산 농수산물에 방사능 위험성 입증못햇고 수많은 논문들이 뒷받침하는데 방사능이랑 방사선이 뭐가 다른지도 모르는 ''한국 대깨문'''들만 후쿠시마 방사능 거림 ㅋㅋㅋ 니들은 후쿠시마 방사능이 그렇게 위험하면 그동네랑 같은 해류타고 겨우 수백키로 떨어진 한반도에서 어떻게 밥먹고 사냐? ㅋㅋㅋ 후쿠시마에서 피폭되서 사망한사람 한명이라도 본사람??? ㅋㅋㅋㅋ\n", "인종/지역Y/N": "Y", "정치성향Y/N": "Y", "혐오 클래스": "Y", "특정 집단": "N", "그 외": "N"}