{"모욕": 2, "욕설": 0, "외설": 0, "폭력위협/범죄조장": 0, "성혐오": 0, "연령": 0, "인종/지역": 0, "장애": 0, "종교": 0, "정치성향": 0, "직업": 0, "1단계Y/N": "Y", "2-1단계Y/N": "Y", "2-2단계Y/N": "Y", "문장": "''정권나팔 방송'''이 이렇게 무능하고 세계에 ''쪽'''을 ''팔음''' SNS에서 MBC ''조롱''' ''난리'''도 아님 올림픽 선수들을 응원해주고 싶어도 MBC 보면 ''힘'''''빠짐''' 다른 채널에서 보시길 그리고 MBC KBS 정권 ''나팔부대'''는 이제 ''폐지'''해도 될때임 그냥 ''사라져'''주세요~", "대상하이라이트": "정권나팔 방송이 이렇게 무능하고 세계에 쪽을 팔음 SNS에서 ''MBC''' 조롱 난리도 아님 올림픽 선수들을 응원해주고 싶어도 ''MBC''' 보면 힘빠짐 다른 채널에서 보시길 그리고 ''MBC''' ''KBS''' 정권 나팔부대는 이제 폐지해도 될때임 그냥 사라져주세요~", "혐오 클래스": "N", "특정 집단": "N", "그 외": "Y"}