{"모욕": 2, "욕설": 0, "외설": 0, "폭력위협/범죄조장": 3, "성혐오": 3, "연령": 0, "인종/지역": 0, "장애": 0, "종교": 0, "정치성향": 0, "직업": 0, "1단계Y/N": "Y", "2-1단계Y/N": "Y", "2-2단계Y/N": "Y", "문장": "저런 ''범죄'''는 한국에서 한 번 정도 ''일어나도''' ''괜찮'''을거 같다.. 군대도 안가고 20대에 2년 남자보다 출발선도 빠르면서 차별받는다고 우기고 모든 혜택은 다 받아가는 행복한 한국여성들~ 그냥 다 '''죽여버리'''도 싶다..", "대상하이라이트": "저런 범죄는 한국에서 한 번 정도 일어나도 괜찮을거 같다.. 군대도 안가고 20대에 2년 남자보다 출발선도 빠르면서 차별받는다고 우기고 모든 혜택은 다 받아가는 행복한 ''한국여성'''들~ 그냥 다 죽여버리도 싶다..", "성혐오Y/N": "Y", "혐오 클래스": "Y", "특정 집단": "N", "그 외": "N"}