{"모욕": 1, "욕설": 0, "외설": 0, "폭력위협/범죄조장": 0, "성혐오": 0, "연령": 0, "인종/지역": 0, "장애": 0, "종교": 2, "정치성향": 0, "직업": 0, "1단계Y/N": "Y", "2-1단계Y/N": "N", "2-2단계Y/N": "N", "문장": "저런 종교들의 특징 자신들의 종교만 종교고 다른 종교들은 인정도 안함 종교의 기본 교리도 모르는 것들 다 한곳에서 파생됐으면서 갈등만 만드는 종교들은 지구에서 사라져야지", "대상하이라이트": "저런 종교들의 특징 자신들의 종교만 종교고 다른 종교들은 인정도 안함 종교의 기본 교리도 모르는 것들 다 한곳에서 파생됐으면서 갈등만 만드는 종교들은 지구에서 사라져야지", "성혐오Y/N": "N", "연령Y/N": "N", "인종/지역Y/N": "N", "장애Y/N": "N", "종교Y/N": "Y", "정치성향Y/N": "N", "직업Y/N": "N", "혐오 클래스": "Y", "특정 집단": "N", "그 외": "N"}