{"모욕": 1, "욕설": 0, "외설": 0, "폭력위협/범죄조장": 0, "성혐오": 0, "연령": 0, "인종/지역": 0, "장애": 0, "종교": 0, "정치성향": 0, "직업": 0, "1단계Y/N": "Y", "2-1단계Y/N": "Y", "2-2단계Y/N": "Y", "문장": "텔레반은 미국으로부터 무기 지원 받았는데~ 어떤 이유인지 #@이름#을 제거하려하자~ 9.11하고 관련이 있는지 모르지만~ 중동에서 많은 사람이 죽었다. 이제 아프칸을 접수했으니~ 조용할 날이 없겠다. 무슬림 원리주의자들~ 나라를 위해 죽으면 천국간다고~ 여자도 자살폭탄을 서슴치 않으니~", "대상하이라이트": "텔레반은 미국으로부터 무기 지원 받았는데~ 어떤 이유인지 #@이름#을 제거하려하자~ 9.11하고 관련이 있는지 모르지만~ 중동에서 많은 사람이 죽었다. 이제 아프칸을 접수했으니~ 조용할 날이 없겠다. 무슬림 원리주의자들~ 나라를 위해 죽으면 천국간다고~ 여자도 자살폭탄을 서슴치 않으니~", "혐오 클래스": "N", "특정 집단": "Y", "그 외": "N"}