{"모욕": 1, "욕설": 0, "외설": 0, "폭력위협/범죄조장": 0, "성혐오": 0, "연령": 0, "인종/지역": 2, "장애": 0, "종교": 0, "정치성향": 0, "직업": 0, "1단계Y/N": "Y", "2-1단계Y/N": "Y", "2-2단계Y/N": "Y", "문장": "그저 수단과방법을 가리지않고 메달만 집착하는 ''오랑캐'''들의 썩은 인간들 기사 보고싶지않다 ''중국놈'''들이 너무 많이 들여온 ''죄인놈'''부터 끌어내려야한다 전국적으로 차이나타운 지어서 중국화 시키려하는 ''중국놈'''정치''개'''들 싸그리 끌어내려서 극형에 처해야한다", "대상하이라이트": "그저 수단과방법을 가리지않고 메달만 집착하는 오랑캐들의 썩은 인간들 기사 보고싶지않다 ''중국놈'''들이 너무 많이 들여온 죄인놈부터 끌어내려야한다 전국적으로 차이나타운 지어서 중국화 시키려하는 ''중국놈'''정치개들 싸그리 끌어내려서 극형에 처해야한다", "인종/지역Y/N": "Y", "혐오 클래스": "Y", "특정 집단": "N", "그 외": "N"}