{"모욕": 1, "욕설": 0, "외설": 0, "폭력위협/범죄조장": 0, "성혐오": 0, "연령": 0, "인종/지역": 0, "장애": 0, "종교": 0, "정치성향": 2, "직업": 0, "1단계Y/N": "Y", "2-1단계Y/N": "Y", "2-2단계Y/N": "Y", "문장": "그 정도는 애교 아닐까? #@이름# 수괴가 있는 더듬는 ''성폭력당'''은 지난 총선에서 우리의적은 국민의힘(신한국당?)이 아니라 일본이다 라고하여 일본에 대한 적개심 온국민에게 호소해서 대 승리를 거두고, 차기대선에서 또다시 일본과의 감정을 국민에게 심고자 일본이 지금 쳐 들어오는것도 아닌데 독도방어훈련하고 일본스가와 전쟁이라도 할듯 건드려봐도 이젠 국민이 호응을 안하니 어론 매체를 통해 일본만건드려 반일감정 호소하는데 통하지않는다.", "대상하이라이트": "그 정도는 애교 아닐까? #''@이름'''# 수괴가 있는 더듬는 성폭력당은 지난 총선에서 우리의적은 국민의힘(신한국당?)이 아니라 일본이다 라고하여 일본에 대한 적개심 온국민에게 호소해서 대 승리를 거두고, 차기대선에서 또다시 일본과의 감정을 국민에게 심고자 일본이 지금 쳐 들어오는것도 아닌데 독도방어훈련하고 일본스가와 전쟁이라도 할듯 건드려봐도 이젠 국민이 호응을 안하니 어론 매체를 통해 일본만건드려 반일감정 호소하는데 통하지않는다.", "정치성향Y/N": "Y", "혐오 클래스": "Y", "특정 집단": "N", "그 외": "N"}