{"모욕": 1, "욕설": 2, "외설": 0, "폭력위협/범죄조장": 1, "성혐오": 0, "연령": 0, "인종/지역": 2, "장애": 0, "종교": 0, "정치성향": 0, "직업": 0, "1단계Y/N": "Y", "2-1단계Y/N": "Y", "2-2단계Y/N": "Y", "문장": "중국이 주는 지원과 돈은 혹독한 댓가를 치르거나 몇백배 더 큰 손실과 함께 내정간섭 및 이권사업 독점이라는 중국에 속내를 감당해야 할것입니다 캄보디아가 좋은 예로 이제 캄보디아는 이름만 캄보디아지 중국이 정치 경제 군을 모두 장악하고 빨대꽂고 쪽쪽 ''빨아'''먹고 있는 나라입니다 중국은 온세상에 ''재앙'''입니다 언능 ''처리'''합시다", "대상하이라이트": "중국이 주는 지원과 돈은 혹독한 댓가를 치르거나 몇백배 더 큰 손실과 함께 내정간섭 및 이권사업 독점이라는 중국에 속내를 감당해야 할것입니다 캄보디아가 좋은 예로 이제 캄보디아는 이름만 캄보디아지 ''중국'''이 정치 경제 군을 모두 장악하고 빨대꽂고 쪽쪽 빨아먹고 있는 나라입니다 ''중국'''은 온세상에 재앙입니다 언능 처리합시다", "인종/지역Y/N": "Y", "혐오 클래스": "Y", "특정 집단": "Y", "그 외": "N"}