{"모욕": 2, "욕설": 0, "외설": 0, "폭력위협/범죄조장": 0, "성혐오": 0, "연령": 0, "인종/지역": 0, "장애": 0, "종교": 0, "정치성향": 3, "직업": 0, "1단계Y/N": "Y", "2-1단계Y/N": "N", "2-2단계Y/N": "Y", "문장": "뭐..''개돼지''' 국민들이 냄비에 서서히 익어가는 ''개구리'''처럼 세뇌돼고 있는거지. 하여간 한번도 경험하지 못한 나라를 ''뭉가'''가 몇년만에 만들다니..정말 대단하다!!!", "대상하이라이트": "뭐..개돼지 국민들이 냄비에 서서히 익어가는 개구리처럼 세뇌돼고 있는거지. 하여간 한번도 경험하지 못한 나라를 뭉가가 몇년만에 만들다니..정말 대단하다!!!", "성혐오Y/N": "N", "연령Y/N": "N", "인종/지역Y/N": "N", "장애Y/N": "N", "종교Y/N": "N", "정치성향Y/N": "Y", "직업Y/N": "N", "혐오 클래스": "Y", "특정 집단": "N", "그 외": "N"}