{"모욕": 1, "욕설": 1, "외설": 0, "폭력위협/범죄조장": 0, "성혐오": 0, "연령": 0, "인종/지역": 0, "장애": 0, "종교": 0, "정치성향": 0, "직업": 0, "1단계Y/N": "Y", "2-1단계Y/N": "Y", "2-2단계Y/N": "Y", "문장": "코로나때메거절이라고 하기엔 표정부터 ''똥 십'''고 ㅋㅋㅋ악수말고 주먹치기로 다른방식으로 할수도 있는데 너무비매너를 보여준 표본이다 저런선수는 선수 할 ''자격이없'''다. 져서 기분은 않좋겠지만 상대방이 먼저와서 위로를건냈는데 저건아니지….#@이름#가 #@이름# 한테 한걸 보고 배워라", "대상하이라이트": "코로나때메거절이라고 하기엔 표정부터 똥 십고 ㅋㅋㅋ악수말고 주먹치기로 다른방식으로 할수도 있는데 너무비매너를 보여준 표본이다 저런선수는 선수 할 자격이없다. 져서 기분은 않좋겠지만 상대방이 먼저와서 위로를건냈는데 저건아니지….''#@이름#'''가 #@이름# 한테 한걸 보고 배워라", "혐오 클래스": "N", "특정 집단": "N", "그 외": "Y"}