{"모욕": 2, "욕설": 0, "외설": 0, "폭력위협/범죄조장": 0, "성혐오": 0, "연령": 0, "인종/지역": 0, "장애": 0, "종교": 0, "정치성향": 0, "직업": 1, "1단계Y/N": "Y", "2-1단계Y/N": "Y", "2-2단계Y/N": "N", "문장": "현재 전국 요양병원 털면 거의 대부분 저런식으로 걸린다. 이사라고 홈피에 떡하니 사진올린 작사들은 전부 사무장들이고.....  표적수사 타겟으로 잡아들이지말고 전수조사해서 다 바로잡아라.   물론 정부가 할 생각도 없겠지만. 왜냐고? 전부 문닫야하니까 의료공백생기니까.", "대상하이라이트": "현재 전국 ''요양병원''' 털면 거의 대부분 저런식으로 걸린다. 이사라고 홈피에 떡하니 사진올린 작사들은 전부 사무장들이고..... 표적수사 타겟으로 잡아들이지말고 전수조사해서 다 바로잡아라. 물론 ''정부'''가 할 생각도 없겠지만. 왜냐고? 전부 문닫야하니까 의료공백생기니까.", "직업Y/N": "Y", "혐오 클래스": "Y", "특정 집단": "N", "그 외": "N"}