{"모욕": 2, "욕설": 2, "외설": 0, "폭력위협/범죄조장": 0, "성혐오": 0, "연령": 0, "인종/지역": 0, "장애": 0, "종교": 0, "정치성향": 1, "직업": 0, "1단계Y/N": "Y", "2-1단계Y/N": "Y", "2-2단계Y/N": "Y", "문장": "#@이름#과 국민의짐당이 제대로 한건 하는구나..@@서울시. 방역 풀어놨다가 더. 조여서 소상공인 다 죽이는구나..@@이래서 선거 잘해야된다....@@@@@무조건 ''여론몰이'''해서 ''국짐당''' 뽑으면 나라 또 ''닭대가리식'''으로 ''말아 먹'''는다.@@", "대상하이라이트": "#@이름#과 ''국민의짐당'''이 제대로 한건 하는구나..@@서울시. 방역 풀어놨다가 더. 조여서 소상공인 다 죽이는구나..@@이래서 선거 잘해야된다....@@@@@무조건 여론몰이해서 ''국짐당''' 뽑으면 나라 또 닭대가리식으로 말아 먹는다.@@", "정치성향Y/N": "Y", "혐오 클래스": "Y", "특정 집단": "N", "그 외": "N"}