{"모욕": 2, "욕설": 1, "외설": 0, "폭력위협/범죄조장": 0, "성혐오": 0, "연령": 0, "인종/지역": 0, "장애": 0, "종교": 0, "정치성향": 2, "직업": 0, "1단계Y/N": "Y", "2-1단계Y/N": "Y", "2-2단계Y/N": "Y", "문장": "''적폐'''들아 대통령이 주로 할 일이 외교 국방인데 이''넘'''들은 오직 정치보복만 생각하고 있어 정치탄압 보복 많이했던 #@이름# #@이름# #@이름# 어떤''꼬라지'''로 전락했는지 잘 봐라 그 주변사람까지 폭망했다 그리고 #@이름# 대통령 과 그 가족 , #@이름# 총리를 강압 불법 수사한 그세력들 어찌됐는지 잘 봐라 정치보복 좋을 것 같지 급하게 망하는 길이 정치보복이다 ''썩'''은 동아줄 #@이름#이 옆에 있는 사람들도 다 함께 침몰할끼다", "대상하이라이트": "''적폐'''들아 대통령이 주로 할 일이 외교 국방인데 이넘들은 오직 정치보복만 생각하고 있어 정치탄압 보복 많이했던 ''#@이름#''' ''#@이름#''' ''#@이름#''' 어떤꼬라지로 전락했는지 잘 봐라 그 주변사람까지 폭망했다 그리고 #@이름# 대통령 과 그 가족 , #@이름# 총리를 강압 불법 수사한 그세력들 어찌됐는지 잘 봐라 정치보복 좋을 것 같지 급하게 망하는 길이 정치보복이다 썩은 동아줄 ''#@이름#'''이 옆에 있는 사람들도 다 함께 침몰할끼다", "정치성향Y/N": "Y", "혐오 클래스": "Y", "특정 집단": "N", "그 외": "N"}