{"모욕": 2, "욕설": 0, "외설": 0, "폭력위협/범죄조장": 0, "성혐오": 2, "연령": 0, "인종/지역": 0, "장애": 1, "종교": 0, "정치성향": 0, "직업": 0, "1단계Y/N": "Y", "2-1단계Y/N": "Y", "2-2단계Y/N": "Y", "문장": "태초에 서로 사랑하고 존중하고 아껴줘야 하는 남녀가 있었으니 대대손손 서로를 위해 희생하고 노력하며 가정과 사회를 이끌어 갔으나, 생물학적으로는 여성이오 외모는 어느 남자들 보다 못생긴 이기적인 존재가 있었으니 그는 ''메퇘지'''로 남자들에게는 선택받지 못하고 정상적인 여성들에게는 인정받지 못하는 동물이 있었습니다. ''메퇘지'''들은 아름다운 여성은 남자들의 성 노리개로 비하하고 남성들은 잠재적 가해자로 둔갑시켜 이들을 이간질 하고 있습니다. 언제까지 이런 농락에 놀아나실겁니까? 여성인권 신장은 필요합니다만 ''메갈'''의 ''페미니즘'''은 ''정신병'''입니다.\n", "대상하이라이트": "태초에 서로 사랑하고 존중하고 아껴줘야 하는 남녀가 있었으니 대대손손 서로를 위해 희생하고 노력하며 가정과 사회를 이끌어 갔으나, 생물학적으로는 여성이오 외모는 어느 남자들 보다 못생긴 이기적인 존재가 있었으니 그는 ''메퇘지'''로 남자들에게는 선택받지 못하고 정상적인 여성들에게는 인정받지 못하는 동물이 있었습니다. ''메퇘지'''들은 아름다운 여성은 남자들의 성 노리개로 비하하고 남성들은 잠재적 가해자로 둔갑시켜 이들을 이간질 하고 있습니다. 언제까지 이런 농락에 놀아나실겁니까? 여성인권 신장은 필요합니다만 ''메갈'''의 페미니즘은 정신병입니다.\n", "성혐오Y/N": "Y", "장애Y/N": "Y", "혐오 클래스": "Y", "특정 집단": "N", "그 외": "N"}