{"모욕": 2, "욕설": 1, "외설": 0, "폭력위협/범죄조장": 0, "성혐오": 0, "연령": 0, "인종/지역": 0, "장애": 0, "종교": 0, "정치성향": 0, "직업": 0, "1단계Y/N": "Y", "2-1단계Y/N": "Y", "2-2단계Y/N": "Y", "문장": "참나..조선시대도 아니고 이게 무슨 집안망신이냐...형이라는게 동생''등골'''쏙''빼먹'''고 자식이란것들도 마치 자기부모가 번돈마냥 ''짓거리'''고다니고.창피한줄모르고.지친구들이이제다알텐데어쩌냐 그''년'''인생ㅋㅋ.세상 ''천박한'''것들이..친 형제라는게 믿어지지가않음..#@이름#씨 꼭 승소하셔서 지금까지 청춘 다 받쳐서 번돈. 전부 회수하시길 응원합니다. 본인인생이 먼저입니다. 젊은시절 열심히 일했던때를 잊지말고 꼭 !!! 반드시 회수하세요!!! 응원합니다~!!!", "대상하이라이트": "참나..조선시대도 아니고 이게 무슨 집안망신이냐...''형'''이라는게 동생등골쏙빼먹고 ''자식이란것'''들도 마치 자기부모가 번돈마냥 짓거리고다니고.창피한줄모르고.지친구들이이제다알텐데어쩌냐 그년인생ㅋㅋ.세상 ''천박한것'''들이..친 형제라는게 믿어지지가않음..#@이름#씨 꼭 승소하셔서 지금까지 청춘 다 받쳐서 번돈. 전부 회수하시길 응원합니다. 본인인생이 먼저입니다. 젊은시절 열심히 일했던때를 잊지말고 꼭 !!! 반드시 회수하세요!!! 응원합니다~!!!", "혐오 클래스": "N", "특정 집단": "N", "그 외": "Y"}