{"모욕": 1, "욕설": 0, "외설": 0, "폭력위협/범죄조장": 0, "성혐오": 0, "연령": 1, "인종/지역": 0, "장애": 0, "종교": 0, "정치성향": 0, "직업": 0, "1단계Y/N": "Y", "2-1단계Y/N": "N", "2-2단계Y/N": "Y", "문장": "팩트) 실제로 숟가락 얻는게 아닌 정말로 청년비서관 주도로 한거 일시이정도 호들갑으로 끝내지 않음. 이준석 욕하지만 이준석정도 되는 인재가 민주당에 있었으면 이미 2030 외엔 뒷방늙은이 취급하는 정책 내면서 유세 개쩔게함", "대상하이라이트": "팩트) 실제로 숟가락 얻는게 아닌 정말로 청년비서관 주도로 한거 일시이정도 호들갑으로 끝내지 않음. 이준석 욕하지만 이준석정도 되는 인재가 민주당에 있었으면 이미 2030 외엔 뒷방늙은이 취급하는 정책 내면서 유세 개쩔게함", "성혐오Y/N": "N", "연령Y/N": "Y", "인종/지역Y/N": "N", "장애Y/N": "N", "종교Y/N": "N", "정치성향Y/N": "N", "직업Y/N": "N", "혐오 클래스": "N", "특정 집단": "N", "그 외": "N"}