{"모욕": 2, "욕설": 1, "외설": 0, "폭력위협/범죄조장": 0, "성혐오": 0, "연령": 0, "인종/지역": 0, "장애": 0, "종교": 0, "정치성향": 1, "직업": 0, "1단계Y/N": "Y", "2-1단계Y/N": "Y", "2-2단계Y/N": "Y", "문장": "왜..''좀비'''된다하지그러냐?에어컨하고틀어서 기침하는사람.비염있어 코가뒤로넘어가는사람.사래걸려 기침하는사람등등 글엄 델타냐??''개'''소리를하고있어.차라리.국민들이 정부에서일하는게더.나을듯하다.코로나에서 델타로 변형됬었담서 #@이름# 사고반장 넌 마스크안끼냐??이것들 장난''똥'''''싸리'''나.국민들 달달볶지마라 살기도힘든데.백신맞아 젓었다.핑계되지마라.욕나오게하고있어", "대상하이라이트": "왜..좀비된다하지그러냐?에어컨하고틀어서 기침하는사람.비염있어 코가뒤로넘어가는사람.사래걸려 기침하는사람등등 글엄 델타냐??개소리를하고있어.차라리.국민들이 ''정부'''에서일하는게더.나을듯하다.코로나에서 델타로 변형됬었담서 ''#@이름#''' 사고반장 넌 마스크안끼냐??이것들 장난똥싸리나.국민들 달달볶지마라 살기도힘든데.백신맞아 젓었다.핑계되지마라.욕나오게하고있어", "정치성향Y/N": "Y", "혐오 클래스": "Y", "특정 집단": "N", "그 외": "Y"}