{"모욕": 1, "욕설": 2, "외설": 0, "폭력위협/범죄조장": 2, "성혐오": 0, "연령": 0, "인종/지역": 0, "장애": 0, "종교": 0, "정치성향": 0, "직업": 0, "1단계Y/N": "Y", "2-1단계Y/N": "Y", "2-2단계Y/N": "Y", "문장": "여러분…갈등유발하는 ''새키'''들은 그냥 중국인 또는 화교 또는 교포 OOO ''드러'''운 ''새키'''들이라고 생각하시면 됩니다 물론 페미OOO들도있지만 갈등도장은 한국''년'''들만이하는게 아닙니다. 제 글에 싫어요기 찍히는 숫자를 보면 아실고같아요 ㅎㅎ 그리고 페미,화교,중국OOO들 걍 다 ''뒤'''져 화교포함^^", "대상하이라이트": "여러분…갈등유발하는 새키들은 그냥 ''중국인''' 또는 ''화교''' 또는 ''교포''' OOO 드러운 새키들이라고 생각하시면 됩니다 물론 ''페미'''OOO들도있지만 갈등도장은 한국년들만이하는게 아닙니다. 제 글에 싫어요기 찍히는 숫자를 보면 아실고같아요 ㅎㅎ 그리고 페미,화교,중국OOO들 걍 다 뒤져 화교포함^^", "혐오 클래스": "N", "특정 집단": "Y", "그 외": "N"}