{"모욕": 1, "욕설": 1, "외설": 0, "폭력위협/범죄조장": 0, "성혐오": 0, "연령": 0, "인종/지역": 0, "장애": 0, "종교": 0, "정치성향": 1, "직업": 0, "1단계Y/N": "Y", "2-1단계Y/N": "Y", "2-2단계Y/N": "Y", "문장": "도지사를 빨리 바꿔야 한다. 제주도에는 관심없고, 정치욕심만 부리는 인간을 도지사에 앉힌 ''놈'''들...잘 보고 있냐...니 한표가 이렇게 중요한거다. 다음에는 혈연, 지연, 학연 이런거 따지지말고, 제대로 된 인간을 도지사에 앉히자.", "대상하이라이트": "''도지사'''를 빨리 바꿔야 한다. ''제주도에는 관심없고, 정치욕심만 부리는 인간을 도지사에 앉힌 놈'''들...잘 보고 있냐...니 한표가 이렇게 중요한거다. 다음에는 혈연, 지연, 학연 이런거 따지지말고, 제대로 된 인간을 도지사에 앉히자.", "정치성향Y/N": "Y", "혐오 클래스": "Y", "특정 집단": "Y", "그 외": "N"}