{"모욕": 1, "욕설": 1, "외설": 0, "폭력위협/범죄조장": 0, "성혐오": 0, "연령": 0, "인종/지역": 0, "장애": 0, "종교": 0, "정치성향": 2, "직업": 0, "1단계Y/N": "Y", "2-1단계Y/N": "Y", "2-2단계Y/N": "Y", "문장": "저런기준을 들이대면 현 국회의원들 감방 들어갈 사람 많네~~역시 정권에 따라 법을 적용하는 잣대가 다른듯. #@이름#에 흠짓 내서 대선주자 탈락 시킬 의도 인게 눈에 다보여~~ 왜냐고? #@이름#이 대통령 되면 자기들 감옥갈 인간들 많거든. 국민들을 아직도 ''개돼지'''로 보고 있는 정권이야. 여론 몰이해서 #@이름# 만큼은 대통령 못되게 하려고. 다시는 속지말자. 좌측 인간들은 지들 정권유지 하려고 사람 목숨따윈 안중에도 없는 자들이야.", "대상하이라이트": "저런기준을 들이대면 현 국회의원들 감방 들어갈 사람 많네~~역시 정권에 따라 법을 적용하는 잣대가 다른듯. #@이름#에 흠짓 내서 대선주자 탈락 시킬 의도 인게 눈에 다보여~~ 왜냐고? #@이름#이 대통령 되면 자기들 감옥갈 인간들 많거든. 국민들을 아직도 개돼지로 보고 있는 정권이야. 여론 몰이해서 #@이름# 만큼은 대통령 못되게 하려고. 다시는 속지말자. ''좌측 인간'''들은 지들 정권유지 하려고 사람 목숨따윈 안중에도 없는 자들이야.", "정치성향Y/N": "Y", "혐오 클래스": "Y", "특정 집단": "N", "그 외": "N"}