{"모욕": 3, "욕설": 3, "외설": 0, "폭력위협/범죄조장": 0, "성혐오": 0, "연령": 0, "인종/지역": 0, "장애": 0, "종교": 0, "정치성향": 0, "직업": 0, "1단계Y/N": "Y", "2-1단계Y/N": "Y", "2-2단계Y/N": "Y", "문장": "저 인간 삼족을 ''멸해'''야하는 이유. 첫째 ''추악'''한 외모로 국민들 시력저하와 구토유발로 인한 심각한 환경파괴의 주범임. 둘째 ''사이비교주'''와 같은 교묘한 말장난으로 국민들 가슴을 멍들게 하고 심신을 피로하게 함. 셋째, 일반월급쟁이의 몇십배를 받아 ''쳐먹'''어 국민혈세를 낭비케함. 결정적으로 밥상을 수도없이 엎게 만듬. ''돼지'''도 동족 싫다고 도망갈 ''쳐''' ''죽일''' ''짐승'''.", "대상하이라이트": "저 인간 삼족을 멸해야하는 이유. 첫째 추악한 외모로 국민들 시력저하와 구토유발로 인한 심각한 환경파괴의 주범임. 둘째 ''사이비교주'''와 같은 교묘한 말장난으로 국민들 가슴을 멍들게 하고 심신을 피로하게 함. 셋째, 일반월급쟁이의 몇십배를 받아 쳐먹어 국민혈세를 낭비케함. 결정적으로 밥상을 수도없이 엎게 만듬. 돼지도 동족 싫다고 도망갈 쳐 죽일 짐승.", "혐오 클래스": "N", "특정 집단": "Y", "그 외": "N"}