{"모욕": 2, "욕설": 2, "외설": 0, "폭력위협/범죄조장": 0, "성혐오": 0, "연령": 0, "인종/지역": 0, "장애": 0, "종교": 0, "정치성향": 3, "직업": 0, "1단계Y/N": "Y", "2-1단계Y/N": "Y", "2-2단계Y/N": "Y", "문장": "권력의시녀 앞잡이 질이나 하는 엠비스 커버스는 지금 당장 문을 닫아라 하긴 닫든말든 보지 않으니 관계는 없다만 커버스''새히'''들은 시청료를 받으려면 정당하게 받지 어디 꼼수로 다른 세금에 포함시켜서 받는지 그러면 ''재앙이'''''넘'''과 ''대깨문'''''넘'''들은 그러겠지 그전 정권때 부터 그래왔다고 그러면 그렇게 욕하던 전정권과 뭐가 다른가 지''넘'''들은 정의로운척 깨끗한척 온갖 척이란 척은 다하면서 정작 하는짓은 ''양아치'''다 엠버스 커버스 다 ''망해'''라", "대상하이라이트": "권력의시녀 앞잡이 질이나 하는 ''엠비스 커버스'''는 지금 당장 문을 닫아라 하긴 닫든말든 보지 않으니 관계는 없다만 ''커버스'''새히들은 시청료를 받으려면 정당하게 받지 어디 꼼수로 다른 세금에 포함시켜서 받는지 그러면 ''재앙이넘'''과 ''대깨문넘'''들은 그러겠지 그전 정권때 부터 그래왔다고 그러면 그렇게 욕하던 전정권과 뭐가 다른가 지넘들은 정의로운척 깨끗한척 온갖 척이란 척은 다하면서 정작 하는짓은 양아치다 ''엠버스 커버스''' 다 망해라", "정치성향Y/N": "Y", "혐오 클래스": "N", "특정 집단": "Y", "그 외": "Y"}