{"모욕": 1, "욕설": 0, "외설": 0, "폭력위협/범죄조장": 0, "성혐오": 0, "연령": 0, "인종/지역": 0, "장애": 0, "종교": 0, "정치성향": 1, "직업": 0, "1단계Y/N": "Y", "2-1단계Y/N": "Y", "2-2단계Y/N": "N", "문장": "헬스장 영업제한 자영업자 사장님들 죽겠다고 하니까 펜데믹 상황가운데서도 영업하는 대신 세세하게 방역부탁한다고 나오는 지침인데 이거를 까냐? 아 그냥 해외입국 전부 막고 올스톱셧다운 한달하지 람다 변이까지 생겼다는데 그냥 올스톱가지 왜 이런 지침줘서 조롱받냐 조롱하는 국민 수준 셧다운 못하는 정부  그 국민에 그 정부네", "대상하이라이트": "헬스장 영업제한 자영업자 사장님들 죽겠다고 하니까 펜데믹 상황가운데서도 영업하는 대신 세세하게 방역부탁한다고 나오는 지침인데 이거를 까냐? 아 그냥 해외입국 전부 막고 올스톱셧다운 한달하지 람다 변이까지 생겼다는데 그냥 올스톱가지 왜 이런 지침줘서 조롱받냐 조롱하는 국민 수준 셧다운 못하는 ''정부'''  그 국민에 그 ''정부'''네", "정치성향Y/N": "Y", "혐오 클래스": "Y", "특정 집단": "N", "그 외": "N"}