{"모욕": 2, "욕설": 2, "외설": 0, "폭력위협/범죄조장": 0, "성혐오": 0, "연령": 2, "인종/지역": 0, "장애": 0, "종교": 0, "정치성향": 0, "직업": 0, "1단계Y/N": "Y", "2-1단계Y/N": "Y", "2-2단계Y/N": "Y", "문장": "싹수가 그냥 노란게 아니라 ''샛노랗'''구나 커서 남자 여럿 됀통 골탕먹겠구만 저건 100%부모의 인성교육 부재 탓이다 만약 이글을 부모가 본다는 전제하에 한마디 충고 해야겠다 지금부터 정신바짝 차리고 아이교육 제대로 못시키면 그아이의 앞날은 당신들의 상상을 초월할거요 어차피 낳은자식 제대로좀 키웁시다 내자식이 남에게 손가락질 받는 사람이 되길 원한다면 맘대로 키우시던가 하세요 그만큼 자식교육은 가장 중요한겁니다 내말이 좀 지나쳤을지라도 이해하시고 앙큼한 거짓말에 6개월 옥살이하신분께 사과부터 하시오 어휴 요즘 아이들은 어른을 갗고놀아요.", "대상하이라이트": "싹수가 그냥 노란게 아니라 샛노랗구나 커서 남자 여럿 됀통 골탕먹겠구만 저건 100%부모의 인성교육 부재 탓이다 만약 이글을 ''부모'''가 본다는 전제하에 한마디 충고 해야겠다 지금부터 정신바짝 차리고 아이교육 제대로 못시키면 그아이의 앞날은 당신들의 상상을 초월할거요 어차피 낳은자식 제대로좀 키웁시다 내자식이 남에게 손가락질 받는 사람이 되길 원한다면 맘대로 키우시던가 하세요 그만큼 자식교육은 가장 중요한겁니다 내말이 좀 지나쳤을지라도 이해하시고 앙큼한 거짓말에 6개월 옥살이하신분께 사과부터 하시오 어휴 ''요즘 아이'''들은 어른을 갗고놀아요.", "연령Y/N": "Y", "혐오 클래스": "Y", "특정 집단": "N", "그 외": "Y"}