{"모욕": 1, "욕설": 0, "외설": 0, "폭력위협/범죄조장": 0, "성혐오": 0, "연령": 0, "인종/지역": 0, "장애": 0, "종교": 0, "정치성향": 0, "직업": 2, "1단계Y/N": "Y", "2-1단계Y/N": "Y", "2-2단계Y/N": "N", "문장": "검찰이 #@이름# 사건 같이 검사들 비리는 꼭꼭 숨겨두고 지들 입맛에 맘대로 쭈무르는 빨래줄 형평성을 차단해야 한다 이제는 경찰도 기소권이 있으므로 함부로 못할것이다 여태까지는 지들하고 싶은대로 했지만 어렵다  구태에서 벗어나 공정하게 국민을 위해 일하라 조직을 위해 일하지 말고", "대상하이라이트": "''검찰'''이 #@이름# 사건 같이 검사들 비리는 꼭꼭 숨겨두고 지들 입맛에 맘대로 쭈무르는 빨래줄 형평성을 차단해야 한다 이제는 경찰도 기소권이 있으므로 함부로 못할것이다 여태까지는 지들하고 싶은대로 했지만 어렵다 구태에서 벗어나 공정하게 국민을 위해 일하라 조직을 위해 일하지 말고\n", "직업Y/N": "Y", "혐오 클래스": "Y", "특정 집단": "N", "그 외": "N"}