{"모욕": 2, "욕설": 0, "외설": 0, "폭력위협/범죄조장": 0, "성혐오": 0, "연령": 0, "인종/지역": 0, "장애": 0, "종교": 0, "정치성향": 3, "직업": 0, "1단계Y/N": "Y", "2-1단계Y/N": "Y", "2-2단계Y/N": "Y", "문장": "''바지'''나 ''벗겠다'''는 대통령 후보! ''성추행'''하는 서울시장, 부산시장! 국가를 지키는 우리 젊은이들이 망망대해에서 코로나에 걸리도록 ''방치'''하는 대통령이란 작자! 이들은 우리 젊은이들의 ''미래'''와 ''희망'''을 ''빼앗'''은 우리나라 반만년 역사의 죄인들입니다! 기필코 역사가 그 일당들을 단죄할 것입니다!", "대상하이라이트": "바지나 벗겠다는 ''대통령 후보'''! 성추행하는 ''서울시'''장, ''부산시'''장! 국가를 지키는 우리 젊은이들이 망망대해에서 코로나에 걸리도록 방치하는 ''대통령'''이란 작자! 이들은 우리 젊은이들의 미래와 희망을 빼앗은 우리나라 반만년 역사의 죄인들입니다! 기필코 역사가 그 일당들을 단죄할 것입니다!", "정치성향Y/N": "Y", "혐오 클래스": "Y", "특정 집단": "N", "그 외": "Y"}