{"모욕": 2, "욕설": 1, "외설": 0, "폭력위협/범죄조장": 3, "성혐오": 0, "연령": 0, "인종/지역": 1, "장애": 0, "종교": 0, "정치성향": 2, "직업": 0, "1단계Y/N": "Y", "2-1단계Y/N": "Y", "2-2단계Y/N": "Y", "문장": "군 기강 해이~특히 대한민국의 현재는 전시중인 국가다~휴전선을 가운데 두고 이북 ''똥''' ''돼지'''네 반란군들과 언제 터질지도 모르는 전쟁중이라는 말이다~군법은 민법 보다 상당히 가혹한걸로 알고있다~이런 ''쓰레기''' 같은 ''작자'''들은 재판도 필요없이 군법에 의해 검거즉시 공개 ''총살형'''에 처해야 한다~자살한 여군들은 이미 생을 마감 했으니까 조만간 잊혀 지고 말겠지만 아직도 숱하게 남은 피해자들의 장래는 어떻게 보상해 줄수가 있겠는가?~군대를 이렇듯 당나라 군대로 만든 ''쓰레기''' 정치 ''사깃꾼'''들도 반드시 공개처형 해서 국가의 확고한 기강을 바로 세워야 한다~~", "대상하이라이트": "군 기강 해이~특히 대한민국의 현재는 전시중인 국가다~휴전선을 가운데 두고 ''이북''' 똥 돼지네 반란군들과 언제 터질지도 모르는 전쟁중이라는 말이다~군법은 민법 보다 상당히 가혹한걸로 알고있다~이런 쓰레기 같은 작자들은 재판도 필요없이 군법에 의해 검거즉시 공개 총살형에 처해야 한다~자살한 여군들은 이미 생을 마감 했으니까 조만간 잊혀 지고 말겠지만 아직도 숱하게 남은 피해자들의 장래는 어떻게 보상해 줄수가 있겠는가?~군대를 이렇듯 당나라 군대로 만든 쓰레기 정치 사깃꾼들도 반드시 공개처형 해서 국가의 확고한 기강을 바로 세워야 한다~~", "인종/지역Y/N": "Y", "정치성향Y/N": "Y", "혐오 클래스": "Y", "특정 집단": "N", "그 외": "N"}