{"모욕": 1, "욕설": 0, "외설": 0, "폭력위협/범죄조장": 0, "성혐오": 0, "연령": 0, "인종/지역": 0, "장애": 0, "종교": 0, "정치성향": 2, "직업": 0, "1단계Y/N": "Y", "2-1단계Y/N": "Y", "2-2단계Y/N": "Y", "문장": "이런식의 감성팔인 세월호 그전의 ''좌좀'''선동과 하나 다르지 않아요. 천안함이 어떤 죽음인가요?? 자국을 안전을 위해 희생된 죽음인가? 폄하해서도 안되지만 미화해서도 안되는겁니다. 내편의 죽음은 고귀하고 적편의 죽음은 하찮은건가? 적의 폭침이라 한들 천안함에 어떤 의미부열 할 수 있나? 미연의 그러한 대빌 하지 못한 군을 비판할 일이지 사상자를 미화해서 정치선동하는게 올바른건가?법에 정해진 절차대로 처리하면 될뿐이죠. 이외 추가적인 요군 의문을 낳고 특혜시비가 벌어지죠.", "대상하이라이트": "이런식의 감성팔인 세월호 그전의 ''좌좀'''선동과 하나 다르지 않아요. 천안함이 어떤 죽음인가요?? 자국을 안전을 위해 희생된 죽음인가? 폄하해서도 안되지만 미화해서도 안되는겁니다. 내편의 죽음은 고귀하고 적편의 죽음은 하찮은건가? 적의 폭침이라 한들 천안함에 어떤 의미부열 할 수 있나? 미연의 그러한 대빌 하지 못한 군을 비판할 일이지 사상자를 미화해서 정치선동하는게 올바른건가?법에 정해진 절차대로 처리하면 될뿐이죠. 이외 추가적인 요군 의문을 낳고 특혜시비가 벌어지죠.", "정치성향Y/N": "Y", "혐오 클래스": "Y", "특정 집단": "N", "그 외": "N"}