{"모욕": 1, "욕설": 0, "외설": 0, "폭력위협/범죄조장": 0, "성혐오": 0, "연령": 0, "인종/지역": 0, "장애": 0, "종교": 0, "정치성향": 1, "직업": 0, "1단계Y/N": "Y", "2-1단계Y/N": "Y", "2-2단계Y/N": "N", "문장": "세상이 미쳐돌아가네~유아,청소년,20-30대중에 코로나로 죽은사람있냐?미국에도 단1명도 없다는 보고가 있다. 미친거 아니냐???오히려 백신맞고 부작용으로 죽은 사람이 훨씬 많다는걸 모르냐?대한민국 대통령 잘못뽑아가  죄없는 국민들 아비규환이구나~촛불로 일어선 정부 횃불로 OOO야된다", "대상하이라이트": "세상이 미쳐돌아가네~유아,청소년,20-30대중에 코로나로 죽은사람있냐?미국에도 단1명도 없다는 보고가 있다. 미친거 아니냐???오히려 백신맞고 부작용으로 죽은 사람이 훨씬 많다는걸 모르냐?대한민국 ''대통령''' 잘못뽑아가 죄없는 국민들 아비규환이구나~촛불로 일어선 정부 횃불로 OOO야된다\n", "정치성향Y/N": "Y", "혐오 클래스": "Y", "특정 집단": "N", "그 외": "N"}