{"모욕": 1, "욕설": 0, "외설": 0, "폭력위협/범죄조장": 0, "성혐오": 0, "연령": 0, "인종/지역": 0, "장애": 0, "종교": 0, "정치성향": 1, "직업": 0, "1단계Y/N": "Y", "2-1단계Y/N": "N", "2-2단계Y/N": "N", "문장": "조선은 미해병대 후원이라도 하나? 오스프리 연료라도 좀 채워주나? 미군은 가만 놔둬도 중국에 잘 대응해. 대리만족인지는 몰라도 좀적당히 해라. 기자 사는 게 맘대로 안 되지? 청해부대나 신경써.", "대상하이라이트": "조선은 미해병대 후원이라도 하나? 오스프리 연료라도 좀 채워주나? 미군은 가만 놔둬도 중국에 잘 대응해. 대리만족인지는 몰라도 좀적당히 해라. 기자 사는 게 맘대로 안 되지? 청해부대나 신경써.", "성혐오Y/N": "N", "연령Y/N": "N", "인종/지역Y/N": "N", "장애Y/N": "N", "종교Y/N": "N", "정치성향Y/N": "Y", "직업Y/N": "N", "혐오 클래스": "Y", "특정 집단": "N", "그 외": "N"}