{"모욕": 2, "욕설": 1, "외설": 0, "폭력위협/범죄조장": 0, "성혐오": 0, "연령": 0, "인종/지역": 1, "장애": 0, "종교": 0, "정치성향": 2, "직업": 0, "1단계Y/N": "Y", "2-1단계Y/N": "Y", "2-2단계Y/N": "Y", "문장": "#@이름# 딸 #@이름#가 남편명의 빌라를 #@이름# 명의로 돌려 느닷없이 팔아 먹고 #@이름# 취임과 거의 동시에 태국으로 온가족 망명한 사실은 아직도 의문투성이 ... 이 사건 입에 올리면 더불어당내에선 세월호 선장보다 더 나쁜 ''놈'''이 되버리고 다른 사람이 말하면 무조건 토왜로 몰아 부치는 이 나라 ''빨갱이'''들 ... #@이름# 혼전 까지 악랄하게 깔려는 저급한 놈들 ... #@이름#가 까일까봐 매우 불안해 하니 이제 유치한 짓 그만두고 페어플레이가 뭔지 공부좀 해라 기생충들아\n", "대상하이라이트": "#@이름# 딸 #@이름#가 남편명의 빌라를 #@이름# 명의로 돌려 느닷없이 팔아 먹고 ''#@이름#''' 취임과 거의 동시에 태국으로 온가족 망명한 사실은 아직도 의문투성이 ... 이 사건 입에 올리면 더불어당내에선 세월호 선장보다 더 나쁜 놈이 되버리고 다른 사람이 말하면 무조건 토왜로 몰아 부치는 이 나라 빨갱이들 ... #@이름# 혼전 까지 악랄하게 깔려는 저급한 놈들 ... ''#@이름#'''가 까일까봐 매우 불안해 하니 이제 유치한 짓 그만두고 페어플레이가 뭔지 공부좀 해라 기생충들아\n", "인종/지역Y/N": "Y", "정치성향Y/N": "Y", "혐오 클래스": "Y", "특정 집단": "N", "그 외": "Y"}