{"모욕": 1, "욕설": 0, "외설": 0, "폭력위협/범죄조장": 0, "성혐오": 0, "연령": 0, "인종/지역": 0, "장애": 0, "종교": 0, "정치성향": 1, "직업": 0, "1단계Y/N": "Y", "2-1단계Y/N": "N", "2-2단계Y/N": "Y", "문장": "가족에 폭언하는 사람이 국민들에게는 얼마나 갑질을 해댈지 불문가지 다~설마 가족에게 폭언을 해대면서 국민들은 섬기겠나?~이용해 먹을만큼 이용이나 해먹고 결국 ''재앙'''이 ''*탄''' 이 되는거지~어쩌면 더 심하게 되겠지~재앙이에게 철저히 보복하는것 보는것도 통쾌하겠지만 그러기에는 국민들 피해가 너무클것같네~''좌파''' 한번 더 들어서면 진짜 나라 망한다~그래도 숨은 영웅들이 있어~이번에 나라가 완전히 망가지진 않았는데~한번더 격는다면 진짜 끔찍한 나라가되어~지금도 거리로 내몰리는 국민들~완전히 ''쫄딱''' 망해 묻힐곳도 없어진다\n", "대상하이라이트": "가족에 폭언하는 사람이 국민들에게는 얼마나 갑질을 해댈지 불문가지 다~설마 가족에게 폭언을 해대면서 국민들은 섬기겠나?~이용해 먹을만큼 이용이나 해먹고 결국 재앙이 *탄 이 되는거지~어쩌면 더 심하게 되겠지~재앙이에게 철저히 보복하는것 보는것도 통쾌하겠지만 그러기에는 국민들 피해가 너무클것같네~좌파 한번 더 들어서면 진짜 나라 망한다~그래도 숨은 영웅들이 있어~이번에 나라가 완전히 망가지진 않았는데~한번더 격는다면 진짜 끔찍한 나라가되어~지금도 거리로 내몰리는 국민들~완전히 쫄딱 망해 묻힐곳도 없어진다", "성혐오Y/N": "N", "연령Y/N": "N", "인종/지역Y/N": "N", "장애Y/N": "N", "종교Y/N": "N", "정치성향Y/N": "Y", "직업Y/N": "N", "혐오 클래스": "Y", "특정 집단": "N", "그 외": "N"}