{"모욕": 3, "욕설": 1, "외설": 0, "폭력위협/범죄조장": 0, "성혐오": 0, "연령": 0, "인종/지역": 0, "장애": 0, "종교": 0, "정치성향": 3, "직업": 0, "1단계Y/N": "Y", "2-1단계Y/N": "Y", "2-2단계Y/N": "Y", "문장": "머냐? 얘는? 이런 ''잡것'''들 때문에 여가부 폐지, 통일부 폐지소리가 나오는 거다..장관이라는 작자들이 피해호소인 소릴하지 않나.. 연락사무소가 폭파되도 ''간첩질'''에 눈이 돌아가서 피아구별도 못하질 않나....제대로 대한민국과 국민을 위해 일해라..,그러면 왜 폐지하것냐...\n", "대상하이라이트": "머냐? 얘는? 이런 ''잡것'''들 때문에 여가부 폐지, 통일부 폐지소리가 나오는 거다..장관이라는 작자들이 피해호소인 소릴하지 않나.. 연락사무소가 폭파되도 간첩질에 눈이 돌아가서 피아구별도 못하질 않나....제대로 대한민국과 국민을 위해 일해라..,그러면 왜 폐지하것냐...\n", "정치성향Y/N": "Y", "혐오 클래스": "Y", "특정 집단": "N", "그 외": "N"}