{"모욕": 2, "욕설": 0, "외설": 0, "폭력위협/범죄조장": 0, "성혐오": 0, "연령": 0, "인종/지역": 0, "장애": 0, "종교": 0, "정치성향": 2, "직업": 0, "1단계Y/N": "Y", "2-1단계Y/N": "Y", "2-2단계Y/N": "Y", "문장": "#@이름#는 아마도 #@이름#과 ''더불어공산당'''에게 특명을 받았을거야..'언론에서 띄워주고 역선택 여론조작으로 당대표 만들어줄테니, 어떡하든 #@이름#을 입당시켜 경선에서 여론조작으로 떨어트리자' '우리쪽 청년애들도 당원으로 많이 밀어줘서 너에게 힘을 실어줄테니, 어떡하든 #@이름# 입당시켜 경선에서 죽이자' 하고 말이야....아니면, #@이름# #@이름#의 작품인지도 모르지..#@이름#가 '바른'치킨으로 부르고, #@이름#은 자꾸 '미래'를 짖어대는데..'바른미래당' 이 배신의 ''쓰레기'''들이 국힘을 장악한 현실을 모르시나..국힘입당은 올무고 함정이야.\n", "대상하이라이트": "#@이름#는 아마도 ''#@이름#'''과 ''더불어공산당'''에게 특명을 받았을거야..'언론에서 띄워주고 역선택 여론조작으로 당대표 만들어줄테니, 어떡하든 #@이름#을 입당시켜 경선에서 여론조작으로 떨어트리자' '우리쪽 청년애들도 당원으로 많이 밀어줘서 너에게 힘을 실어줄테니, 어떡하든 #@이름# 입당시켜 경선에서 죽이자' 하고 말이야....아니면, #@이름# #@이름#의 작품인지도 모르지..#@이름#가 '바른'치킨으로 부르고, #@이름#은 자꾸 '미래'를 짖어대는데..'바른미래당' 이 배신의 쓰레기들이 국힘을 장악한 현실을 모르시나..국힘입당은 올무고 함정이야.\n", "정치성향Y/N": "Y", "혐오 클래스": "Y", "특정 집단": "N", "그 외": "Y"}