{"모욕": 2, "욕설": 1, "외설": 0, "폭력위협/범죄조장": 0, "성혐오": 0, "연령": 0, "인종/지역": 0, "장애": 0, "종교": 0, "정치성향": 2, "직업": 0, "1단계Y/N": "Y", "2-1단계Y/N": "Y", "2-2단계Y/N": "Y", "문장": "#@이름# 민주당 5년동안 대체 뭘 잘했나? 인국공 사태, 뽀요이스 원전, 중국몽, 페미니즘과 젠더갈등, 세계 꼴찌 초저출산 0.84명, ''미친''' 집값, #@이름# 논란에 #@이름#, 백신 접종은 ''뒤지게''' 늦어서 oecd 37개국 중 **위. ''대깨'''들은 지금이라도 정신차리세요 진짜 오죽했으면 우리나라 출산율이 세계꼴찌냐\n", "대상하이라이트": "''#@이름#''' ''민주당''' 5년동안 대체 뭘 잘했나? 인국공 사태, 뽀요이스 원전, 중국몽, 페미니즘과 젠더갈등, 세계 꼴찌 초저출산 0.84명, 미친 집값, ''#@이름#''' 논란에 ''#@이름#''', 백신 접종은 뒤지게 늦어서 oecd 37개국 중 **위. ''대깨'''들은 지금이라도 정신차리세요 진짜 오죽했으면 우리나라 출산율이 세계꼴찌냐\n", "정치성향Y/N": "Y", "혐오 클래스": "Y", "특정 집단": "N", "그 외": "N"}