{"모욕": 1, "욕설": 0, "외설": 0, "폭력위협/범죄조장": 0, "성혐오": 0, "연령": 0, "인종/지역": 0, "장애": 0, "종교": 0, "정치성향": 1, "직업": 0, "1단계Y/N": "Y", "2-1단계Y/N": "Y", "2-2단계Y/N": "N", "문장": "#@이름# 지령밭은 정부와 합작한 국방부와 국정원이 대놓고 이적질하고  이런. 무능한 대한민국을 만든 정권은 반드시 처벌해야한다 이나라주변은 일본과 중국 그리고 북한이. 썰치는데 국방부와 군인을 무력회시키는 정부가 정상적인 정부냐", "대상하이라이트": "#@이름# 지령밭은 정부와 합작한 국방부와 국정원이 대놓고 이적질하고 이런. 무능한 대한민국을 만든 ''정권'''은 반드시 처벌해야한다 이나라주변은 일본과 중국 그리고 북한이. 썰치는데 국방부와 군인을 무력회시키는 ''정부'''가 정상적인 정부냐", "정치성향Y/N": "Y", "혐오 클래스": "Y", "특정 집단": "N", "그 외": "N"}