{"모욕": 2, "욕설": 2, "외설": 0, "폭력위협/범죄조장": 3, "성혐오": 0, "연령": 0, "인종/지역": 0, "장애": 0, "종교": 0, "정치성향": 0, "직업": 0, "1단계Y/N": "Y", "2-1단계Y/N": "N", "2-2단계Y/N": "Y", "문장": "K방역 자화자찬 할 때는 언제고, 2,000명 넘어가는데 책임 지는 ''넘'''은 한 명도 없네. ''C8''' 살기 팍팍하다. 정말 갈아 엎고 싶다. 저''C키''' 끌어내려 광화문에서 ''참수해'''야한다. 니 ''넘''' 때문에 수많은 자영업자 피눈물 흘리고 가정파탄 났다. 그런데 저리 뻔뻔 할 수 있나?", "대상하이라이트": "K방역 자화자찬 할 때는 언제고, 2,000명 넘어가는데 책임 지는 넘은 한 명도 없네. C8 살기 팍팍하다. 정말 갈아 엎고 싶다. 저C키 끌어내려 광화문에서 참수해야한다. 니 넘 때문에 수많은 자영업자 피눈물 흘리고 가정파탄 났다. 그런데 저리 뻔뻔 할 수 있나?", "성혐오Y/N": "N", "연령Y/N": "N", "인종/지역Y/N": "N", "장애Y/N": "N", "종교Y/N": "N", "정치성향Y/N": "N", "직업Y/N": "N", "혐오 클래스": "N", "특정 집단": "N", "그 외": "Y"}