{"모욕": 2, "욕설": 1, "외설": 0, "폭력위협/범죄조장": 0, "성혐오": 0, "연령": 0, "인종/지역": 0, "장애": 0, "종교": 0, "정치성향": 0, "직업": 1, "1단계Y/N": "Y", "2-1단계Y/N": "Y", "2-2단계Y/N": "Y", "문장": "#@이름#은 아닌데...왜 ''앞뒤 꽉 막히'''고 규제가 제일이라는 법조인들이 권력을 승계하는 이 ''개'''''꼬라지'''같은 ''악습''' 타파없인 미래 어떠한 것도 기대할 수 없다.#@이름#가 얘기했지? 미국의 유니콘 기업들이 한국에 들어오면 71%가 불법이라고...", "대상하이라이트": "#@이름#은 아닌데...왜 앞뒤 꽉 막히고 규제가 제일이라는 ''법조인'''들이 권력을 승계하는 이 개꼬라지같은 악습 타파없인 미래 어떠한 것도 기대할 수 없다.#@이름#가 얘기했지? 미국의 유니콘 기업들이 한국에 들어오면 71%가 불법이라고...", "직업Y/N": "Y", "혐오 클래스": "Y", "특정 집단": "N", "그 외": "N"}