{"모욕": 2, "욕설": 1, "외설": 0, "폭력위협/범죄조장": 0, "성혐오": 0, "연령": 0, "인종/지역": 3, "장애": 0, "종교": 0, "정치성향": 0, "직업": 3, "1단계Y/N": "Y", "2-1단계Y/N": "Y", "2-2단계Y/N": "Y", "문장": "참으로하심한 의원들이군 ! 한미 연합훈련은북괴의 침략상황을 방어하는 전통적인 한미동맹훈련이다 . ''젖'''비린내나는 #@이름#의 말한마디에 벌발떠는 국회의원들 ! 군대나 갔다왔는가 ? 왜 민주당이 정권만 잡으면했볐정책이다 . 북한을 도와야된다 . 하며 돈과 물자를 퍼주는가 ? 정신차리거라 ! ''북괴'''가 그렇게도 무서운가 ? 그돈으로 무기를 구매해서 군사력좀 키우거라 ? 전방전투사단 기갑부대 해체하지말고 .! 군사강국 으로 대한민국을 세우거라 !", "대상하이라이트": "참으로''하심한 의원'''들이군 ! 한미 연합훈련은북괴의 침략상황을 방어하는 전통적인 한미동맹훈련이다 . 젖비린내나는 #@이름#의 말한마디에 벌발떠는 ''국회의원'''들 ! 군대나 갔다왔는가 ? 왜 민주당이 정권만 잡으면했볐정책이다 . 북한을 도와야된다 . 하며 돈과 물자를 퍼주는가 ? 정신차리거라 ! 북괴가 그렇게도 무서운가 ? 그돈으로 무기를 구매해서 군사력좀 키우거라 ? 전방전투사단 기갑부대 해체하지말고 .! 군사강국 으로 대한민국을 세우거라 !", "인종/지역Y/N": "Y", "직업Y/N": "Y", "혐오 클래스": "Y", "특정 집단": "Y", "그 외": "N"}