{"모욕": 1, "욕설": 0, "외설": 0, "폭력위협/범죄조장": 0, "성혐오": 0, "연령": 0, "인종/지역": 0, "장애": 0, "종교": 0, "정치성향": 0, "직업": 0, "1단계Y/N": "Y", "2-1단계Y/N": "Y", "2-2단계Y/N": "Y", "문장": "진짜일까? 주변에서 #@이름# 못지않게 #@이름#을 싫어하던데. 참 수준 떨어진다. 형수한테 ''보찢'''이라 말하는 자가 지구에서 몇이나 되고 무상연애하고 거짓말만 일삼는 인간을 대통령으로 인정한다는 인간들이 그렇게 많다? 글쎄! 하여튼 #@이름#이 대통령 되는 순간 재산 정리해서 뜬다. 미래가 북한과 같을 것 같기 때문이다.", "대상하이라이트": "진짜일까? 주변에서 #@이름# 못지않게 ''#@이름#'''을 싫어하던데. 참 수준 떨어진다. 형수한테 보찢이라 말하는 자가 지구에서 몇이나 되고 무상연애하고 거짓말만 일삼는 인간을 대통령으로 인정한다는 인간들이 그렇게 많다? 글쎄! 하여튼 ''#@이름#'''이 대통령 되는 순간 재산 정리해서 뜬다. 미래가 북한과 같을 것 같기 때문이다.", "혐오 클래스": "N", "특정 집단": "N", "그 외": "Y"}