{"모욕": 2, "욕설": 0, "외설": 0, "폭력위협/범죄조장": 0, "성혐오": 0, "연령": 0, "인종/지역": 2, "장애": 0, "종교": 0, "정치성향": 2, "직업": 0, "1단계Y/N": "Y", "2-1단계Y/N": "Y", "2-2단계Y/N": "Y", "문장": "''미개한''' ''쪽바리'''답다. 부강하던 나라를 미개한 후진국 만든 극우''쪽바리'''들. 우리도 ''쪽바리'''들 교훈삼아 극우일베. ''무식한''' 검새 ''나부랭이'''가 정권잡는일 없도록 정신 바짝 차려야 한다. 서울시민들 코로나로 난리인데 #@이름#이 안보인다고 난리더라.", "대상하이라이트": "미개한 ''쪽바리'''답다. 부강하던 나라를 미개한 후진국 만든 ''극우쪽바리'''들. 우리도 ''쪽바리'''들 교훈삼아 ''극우일베'''. 무식한 검새 나부랭이가 정권잡는일 없도록 정신 바짝 차려야 한다. 서울시민들 코로나로 난리인데 #@이름#이 안보인다고 난리더라.", "인종/지역Y/N": "Y", "정치성향Y/N": "Y", "혐오 클래스": "Y", "특정 집단": "N", "그 외": "N"}