{"모욕": 1, "욕설": 0, "외설": 0, "폭력위협/범죄조장": 0, "성혐오": 0, "연령": 0, "인종/지역": 0, "장애": 0, "종교": 0, "정치성향": 3, "직업": 0, "1단계Y/N": "Y", "2-1단계Y/N": "Y", "2-2단계Y/N": "Y", "문장": "''대깨문'''들의 댓글 공작을 양념이라 하고 정치동력이라고 하는 사람들의 인수인계로구나. 무엇을 인계하고 인수하는가. 댓글 공작은 민주공화국 민주주의 여론정치를 망치는 독소임은 국민 누구나 아는 상식이다. 댓글 공작 경인선 총책질하다가 아군 총에 맞아 대법원 2년 형 선고를 받았으면, 기본이 되고 부끄러움을 아는 사람이라면 조용히 입감한다. 그런데 무슨 인계인수 한다는 말이 기사로 뜨도록 하느냐. 인격의 기본도 안 되고 민주주의 원칙도 모르고 3권분립과 법의 존엄성도 모르는 자들이 유명정치인이라고 ''나대'''는 우리나라 정치 현실이 씁쓸하다", "대상하이라이트": "''대깨문'''들의 댓글 공작을 양념이라 하고 정치동력이라고 하는 사람들의 인수인계로구나. 무엇을 인계하고 인수하는가. 댓글 공작은 민주공화국 민주주의 여론정치를 망치는 독소임은 국민 누구나 아는 상식이다. 댓글 공작 경인선 총책질하다가 아군 총에 맞아 대법원 2년 형 선고를 받았으면, 기본이 되고 부끄러움을 아는 사람이라면 조용히 입감한다. 그런데 무슨 인계인수 한다는 말이 기사로 뜨도록 하느냐. ''인격의 기본도 안 되고 민주주의 원칙도 모르고 3권분립과 법의 존엄성도 모르는 자'''들이 유명정치인이라고 나대는 우리나라 정치 현실이 씁쓸하다", "정치성향Y/N": "Y", "혐오 클래스": "Y", "특정 집단": "N", "그 외": "N"}