{"모욕": 2, "욕설": 0, "외설": 0, "폭력위협/범죄조장": 0, "성혐오": 0, "연령": 0, "인종/지역": 0, "장애": 0, "종교": 0, "정치성향": 3, "직업": 0, "1단계Y/N": "Y", "2-1단계Y/N": "Y", "2-2단계Y/N": "Y", "문장": "#@이름#?대한민국에서 가장 ''더럽'''고 ''부패한''' 인간입니다..대한민국 역대 대통령중에 가장 ''무능하'''고 ''더러'''운 대통령으로 기록될거임.#@이름# #@이름# 꼴을 보는듯하네 말년에..야당은 드루킹 사건 결과가 나왔으니 #@이름# 탄핵 관련 범국민 추진위원회를 만들어라.그동안 국민들은 코로나 때문에 참았지만 더이상은 아니다.탄핵만이 답이다.", "대상하이라이트": "''#@이름#'''?대한민국에서 가장 ''더럽고 부패한 인간'''입니다..대한민국 역대 대통령중에 ''가장 무능하고 더러운 대통령'''으로 기록될거임.''#@이름#''' ''#@이름#''' 꼴을 보는듯하네 말년에..''야당'''은 드루킹 사건 결과가 나왔으니 ''#@이름#''' 탄핵 관련 범국민 추진위원회를 만들어라.그동안 국민들은 코로나 때문에 참았지만 더이상은 아니다.탄핵만이 답이다.", "정치성향Y/N": "Y", "혐오 클래스": "Y", "특정 집단": "N", "그 외": "N"}