{"모욕": 2, "욕설": 1, "외설": 0, "폭력위협/범죄조장": 0, "성혐오": 0, "연령": 0, "인종/지역": 0, "장애": 0, "종교": 0, "정치성향": 0, "직업": 2, "1단계Y/N": "Y", "2-1단계Y/N": "Y", "2-2단계Y/N": "Y", "문장": "국익을 생각하는 놈들이 대한민국 GDP25%을 하는 기업 총수를 가둬놓냐? 삥띁은 ''놈'''들이 문제지 삔띁긴''놈'''이 잘못이냐? 이 ''대가리'''를 모자걸이로 달고 사는''놈'''들아!!!!!!!!!!!!!!!! 암튼 비논리의 극치인''놈'''들..", "대상하이라이트": "국익을 생각하는 놈들이 대한민국 GDP25%을 하는 기업 총수를 가둬놓냐? 삥띁은 놈들이 문제지 삔띁긴놈이 잘못이냐? 이 대가리를 모자걸이로 달고 사는놈들아!!!!!!!!!!!!!!!! 암튼 비논리의 ''극치인'''놈들..", "직업Y/N": "Y", "혐오 클래스": "Y", "특정 집단": "N", "그 외": "N"}