{"모욕": 2, "욕설": 1, "외설": 0, "폭력위협/범죄조장": 0, "성혐오": 0, "연령": 0, "인종/지역": 0, "장애": 0, "종교": 0, "정치성향": 2, "직업": 0, "1단계Y/N": "Y", "2-1단계Y/N": "Y", "2-2단계Y/N": "Y", "문장": "#@이름#과 180인의 도적들인 ''더듬어 만진당'''이 ''쫄았'''네 ㅋㅋㅋㅋ ㅋㅋㅋㅋ 언론의 자유 통제!! 표현의 자유도 통제!! 국민들의 알 권리도 통제하려는 역사상 ''최악'''의 정권을 시도하려는 ''??''' 수작!!! 전 세계적인 ''??''' 망신 정권이 #@이름#과 주사파 좌파 정권~~~~!!!!! #@이름#과 180인의 도적들의 ''??''' 수작을 ''쓸어버려'''야 나라가 살고 미래세대가 산다~~~~!!!!!!!", "대상하이라이트": "''#@이름#'''과 ''180인의 도적'''들인 ''더듬어 만진당'''이 쫄았네 ㅋㅋㅋㅋ ㅋㅋㅋㅋ 언론의 자유 통제!! 표현의 자유도 통제!! 국민들의 알 권리도 통제하려는 역사상 최악의 정권을 시도하려는 ?? 수작!!! 전 세계적인 ?? 망신 정권이 ''#@이름#'''과 ''주사파 좌파 정권'''~~~~!!!!! ''#@이름#'''과 ''180인의 도적'''들의 ?? 수작을 쓸어버려야 나라가 살고 미래세대가 산다~~~~!!!!!!!", "정치성향Y/N": "Y", "혐오 클래스": "Y", "특정 집단": "N", "그 외": "N"}