{"모욕": 2, "욕설": 0, "외설": 0, "폭력위협/범죄조장": 0, "성혐오": 0, "연령": 0, "인종/지역": 0, "장애": 0, "종교": 0, "정치성향": 0, "직업": 2, "1단계Y/N": "Y", "2-1단계Y/N": "Y", "2-2단계Y/N": "Y", "문장": "국민에게 주는 포상금을 카드결제거부액의 20%가 아니라 벌금1000만원의 20%나 21세기에 걸맞는 210만원으로 국민 모두에게 공정하게 여신금융직원들에게 일처리시켜주세요. 게다가 무엇보다 심보가 예뻐야한다고 기본도덕교육 좀 시켜주세요. 타인이 돈버는 꼴을 보고 기뻐해야 부자동네에 살거라고 논리적인 두뇌가 없으면 좀 배우라고들 해주세요. 맨날 아무나 시샘하는 ''찌질'''''심보'''라서 고객학대하다가 갈수록 직원들이 망하기만 하고 일망치는것 좀 막아주세요. 사악한 직원들이 진짜 답답하고 싫으실듯", "대상하이라이트": "국민에게 주는 포상금을 카드결제거부액의 20%가 아니라 벌금1000만원의 20%나 21세기에 걸맞는 210만원으로 국민 모두에게 공정하게 ''여신금융직원'''들에게 일처리시켜주세요. 게다가 무엇보다 심보가 예뻐야한다고 기본도덕교육 좀 시켜주세요. 타인이 돈버는 꼴을 보고 기뻐해야 부자동네에 살거라고 논리적인 두뇌가 없으면 좀 배우라고들 해주세요. 맨날 아무나 시샘하는 찌질심보라서 고객학대하다가 갈수록 직원들이 망하기만 하고 일망치는것 좀 막아주세요. 사악한 직원들이 진짜 답답하고 싫으실듯", "직업Y/N": "Y", "혐오 클래스": "Y", "특정 집단": "N", "그 외": "N"}