{"모욕": 1, "욕설": 0, "외설": 0, "폭력위협/범죄조장": 0, "성혐오": 0, "연령": 0, "인종/지역": 0, "장애": 0, "종교": 0, "정치성향": 2, "직업": 0, "1단계Y/N": "Y", "2-1단계Y/N": "Y", "2-2단계Y/N": "Y", "문장": "한미동맹이 최우선이 돼야 한다. 이건 ''좌빨'''도 마찬가지. 미국의 핵우산이 없었다면 한국은 과중한 국방비 지출로 경제발전 여력이 없었을 것이고 북한이나 중국에 접수됐을 것. 동시에 변종 관료자본주의 중국의 제국주의적 행태는 역내 불안을 심화할 뿐인데 미국의 원숙한 자유주의와 비교 불가하며 경제적 측면에서도 산업스파이나 도용, 불법복제, 각종 리스크로 이득 보단 실이 크다. 툭하면 한한령을 발하고 보이콧을 국가가 주도하는 나라는 투자국으로서 가치가 없다. 한국은 티벳, 대만, 위구르, 내몽골의 독립을 지지하며 자유주의국가와 연대해야한다.", "대상하이라이트": "한미동맹이 최우선이 돼야 한다. 이건 ''좌빨'''도 마찬가지. 미국의 핵우산이 없었다면 한국은 과중한 국방비 지출로 경제발전 여력이 없었을 것이고 북한이나 중국에 접수됐을 것. 동시에 변종 관료자본주의 중국의 제국주의적 행태는 역내 불안을 심화할 뿐인데 미국의 원숙한 자유주의와 비교 불가하며 경제적 측면에서도 산업스파이나 도용, 불법복제, 각종 리스크로 이득 보단 실이 크다. 툭하면 한한령을 발하고 보이콧을 국가가 주도하는 나라는 투자국으로서 가치가 없다. 한국은 티벳, 대만, 위구르, 내몽골의 독립을 지지하며 자유주의국가와 연대해야한다.", "정치성향Y/N": "Y", "혐오 클래스": "Y", "특정 집단": "N", "그 외": "N"}