{"모욕": 1, "욕설": 0, "외설": 0, "폭력위협/범죄조장": 0, "성혐오": 0, "연령": 0, "인종/지역": 0, "장애": 0, "종교": 0, "정치성향": 0, "직업": 0, "1단계Y/N": "Y", "2-1단계Y/N": "Y", "2-2단계Y/N": "Y", "문장": "윤씨.최씨가 참석하길 꺼리는 이유== 자기 본 모습이 적나라하게 드러난다. 가진 밑천이 없다는게 뽀록나고, 철학,역사관,정치적 자질 등, 기본기가 전혀 않되 있는 모습이 드러나고, 당연 사람들로부터 멸시,모욕을 당할것이 거의 분명함. 즉,이 둘은 애초, 이 쪽에 전혀 깜이 아닌 것이다. 마치 #@이름#*가 전혀 정치인 깜이 아님에도, 주변 ''냥아치'''들에 의해 포장되어, 국민을 속였듯이, 이들 또한 끝까지 국민을 속여 그럴듯하게 보여야만 살아남는 운명이다. 한마디로, 대국민 사기극을 벌여야 함. 그게 통할리는 거의 없다. 이미 #@이름#은 #@이름#", "대상하이라이트": "''윤씨'''.''최씨'''가 참석하길 꺼리는 이유== 자기 본 모습이 적나라하게 드러난다. 가진 밑천이 없다는게 뽀록나고, 철학,역사관,정치적 자질 등, 기본기가 전혀 않되 있는 모습이 드러나고, 당연 사람들로부터 멸시,모욕을 당할것이 거의 분명함. 즉,이 둘은 애초, 이 쪽에 전혀 깜이 아닌 것이다. 마치 ''#@이름#'''*가 전혀 정치인 깜이 아님에도, 주변 냥아치들에 의해 포장되어, 국민을 속였듯이, 이들 또한 끝까지 국민을 속여 그럴듯하게 보여야만 살아남는 운명이다. 한마디로, 대국민 사기극을 벌여야 함. 그게 통할리는 거의 없다. 이미 #@이름#은 #@이름#", "혐오 클래스": "N", "특정 집단": "N", "그 외": "Y"}