{"모욕": 3, "욕설": 1, "외설": 0, "폭력위협/범죄조장": 0, "성혐오": 0, "연령": 0, "인종/지역": 2, "장애": 0, "종교": 0, "정치성향": 0, "직업": 0, "1단계Y/N": "Y", "2-1단계Y/N": "Y", "2-2단계Y/N": "Y", "문장": "진짜 잘 하셨습니다 대한민국 만세 일본''놈'''들 ''개같'''은 버르장머리를 고쳐 줄려면 아직 멀었음 올림픽 기간중 독도 방어훈련이나 거하게 합시다^^ ''폭망'''한 올림픽을 도울 일도 없고 ''쓰레기'''들한테는 ''쓰레기''' 대접이 맞음", "대상하이라이트": "진짜 잘 하셨습니다 대한민국 만세 ''일본놈'''들 개같은 버르장머리를 고쳐 줄려면 아직 멀었음 올림픽 기간중 독도 방어훈련이나 거하게 합시다^^ 폭망한 올림픽을 도울 일도 없고 쓰레기들한테는 쓰레기 대접이 맞음", "인종/지역Y/N": "Y", "혐오 클래스": "Y", "특정 집단": "N", "그 외": "N"}