{"모욕": 2, "욕설": 0, "외설": 0, "폭력위협/범죄조장": 0, "성혐오": 2, "연령": 0, "인종/지역": 0, "장애": 0, "종교": 0, "정치성향": 0, "직업": 0, "1단계Y/N": "Y", "2-1단계Y/N": "Y", "2-2단계Y/N": "Y", "문장": "남혐 나라에서 애 낳기 싫다,, 월급 ''조'''빠지게 벌어오고,, 부인은 애 10개월 뱃속에 품고 사는게 머 그리 어렵다고 감히 하늘같은 남성에게 먹고싶은 것 사오라며 대드는 것을, 뭐 부인 몸이 찢어지건 어쨋건 그래도 당연히 내 성 붙혀 애 낳도록 했더니,, 숏컷 페미들이 웅앵웅 허버허버라고 뭔뜻인진 모르겠지만 감히 남성들의 작은 사이즈를 비하하는,, 이 남혐 대한민국에 어찌 내 유전자를 물려받아 남혐을 당할만한 남자아이를 낳겠는가,,", "대상하이라이트": "남혐 나라에서 애 낳기 싫다,, 월급 조빠지게 벌어오고,, 부인은 애 10개월 뱃속에 품고 사는게 머 그리 어렵다고 감히 하늘같은 남성에게 먹고싶은 것 사오라며 대드는 것을, 뭐 부인 몸이 찢어지건 어쨋건 그래도 당연히 내 성 붙혀 애 낳도록 했더니,, ''숏컷 페미'''들이 웅앵웅 허버허버라고 뭔뜻인진 모르겠지만 감히 남성들의 작은 사이즈를 비하하는,, 이 남혐 대한민국에 어찌 내 유전자를 물려받아 남혐을 당할만한 남자아이를 낳겠는가,,", "성혐오Y/N": "Y", "혐오 클래스": "Y", "특정 집단": "N", "그 외": "N"}