{"모욕": 1, "욕설": 1, "외설": 0, "폭력위협/범죄조장": 0, "성혐오": 0, "연령": 0, "인종/지역": 0, "장애": 0, "종교": 0, "정치성향": 0, "직업": 0, "1단계Y/N": "Y", "2-1단계Y/N": "Y", "2-2단계Y/N": "Y", "문장": "''#@이름#이''' #@이름#대표한데 국회의원선거에서두번 졌다고 모이야 복수야     ''철없'''는 ''찌질이'''        안대표님 독자행보하세요  적극지지합니다      국회의원배지도못단  애하고더이상상종하지마세요   단일화안되고 #@이름#대표님 독자출마하면 저는  안출수 찍습니다     화이팅!!!", "대상하이라이트": "''#@이름#이''' #@이름#대표한데 국회의원선거에서두번 졌다고 모이야 복수야     철없는 찌질이        안대표님 독자행보하세요  적극지지합니다     '' 국회의원배지도못단  애'''하고더이상상종하지마세요   단일화안되고 #@이름#대표님 독자출마하면 저는  안출수 찍습니다     화이팅!!!", "혐오 클래스": "N", "특정 집단": "N", "그 외": "Y"}