{"모욕": 1, "욕설": 0, "외설": 0, "폭력위협/범죄조장": 0, "성혐오": 1, "연령": 0, "인종/지역": 0, "장애": 0, "종교": 0, "정치성향": 0, "직업": 0, "1단계Y/N": "Y", "2-1단계Y/N": "Y", "2-2단계Y/N": "Y", "문장": "좌파의 품격은 이런것이지. #@이름# 탄핵집회때도 수많은 여성혐오를 여과없이 즐기던 좌파들 보고서 좌파여자들 왜 침묵하냐 물어보니 난 동의안해! 라면서도 어떤 비판적 액션도 없던 것들 지난 몇년 동안 찍소리 없는 니들이 여성인권을 언급한다는게 얼마나 비웃긴 일인지 알기를 바란다.", "대상하이라이트": "좌파의 품격은 이런것이지. #@이름# 탄핵집회때도 수많은 여성혐오를 여과없이 즐기던 좌파들 보고서 좌파여자들 왜 침묵하냐 물어보니 난 동의안해! 라면서도 어떤 비판적 액션도 없던 것들 지난 몇년 동안 찍소리 없는 니들이 여성인권을 언급한다는게 얼마나 비웃긴 일인지 알기를 바란다.", "성혐오Y/N": "Y", "혐오 클래스": "Y", "특정 집단": "N", "그 외": "N"}