{"모욕": 2, "욕설": 0, "외설": 0, "폭력위협/범죄조장": 0, "성혐오": 0, "연령": 0, "인종/지역": 0, "장애": 0, "종교": 0, "정치성향": 2, "직업": 0, "1단계Y/N": "Y", "2-1단계Y/N": "Y", "2-2단계Y/N": "Y", "문장": "국민을  속이는  ''사기꾼'''같네요  그래서  국민들  한마디에   안티를   결국   공무원들  소신있게   일할수없게  입에 재갈물리는것   조금이나마   반항하는  공무원은  파면시키고    아주나쁜  정부입니다    국정농단보다  더 나쁜정부이네요    왜  국민을  속이는것으로    나타나면서     현재부터  공무원들은    국민을  위하여   양심적으로   국민들에게   알려주셔서   다음정권으로부터  면책특권을   받으세요~   죽도록  내로남불하는   이유가  여기에  있어서요!!!!!!!!!", "대상하이라이트": "''국민을  속이는  사기꾼'''같네요  그래서  국민들  한마디에   안티를   결국   공무원들  소신있게   일할수없게  입에 재갈물리는것   조금이나마   반항하는  공무원은  파면시키고    아주나쁜  ''정부'''입니다    국정농단보다  더 ''나쁜정부'''이네요    왜  국민을  속이는것으로    나타나면서     현재부터  공무원들은    국민을  위하여   양심적으로   국민들에게   알려주셔서   다음정권으로부터  면책특권을   받으세요~   죽도록  내로남불하는   이유가  여기에  있어서요!!!!!!!!!", "정치성향Y/N": "Y", "혐오 클래스": "Y", "특정 집단": "N", "그 외": "N"}