{"모욕": 1, "욕설": 0, "외설": 0, "폭력위협/범죄조장": 0, "성혐오": 0, "연령": 0, "인종/지역": 0, "장애": 0, "종교": 0, "정치성향": 2, "직업": 0, "1단계Y/N": "Y", "2-1단계Y/N": "Y", "2-2단계Y/N": "Y", "문장": "보수''틀딱'''들아...니들은 정말 보수냐? 아니면 민주딩 ''쁘락치'''냐? 혹은 기회주의자에게 선동당한 ''사이비 신도'''냐?#@이름# #@이름# #@이름#등이 하는 행동들이 보수같냐 #@이름#이 보수같냐?제발 정신 좀 차려라.정권교체 하고싶다며?지금 니들은 대놓고 ''빨갱이''' ''짓''' 안하는 #@이름#을 대통영으로 만드려는거다. 그리고 ''대깨문'''이 하는 짓을 똑같이 따라라며 보수 지지율 박살내는거다 #@이름#이 지지받는 이유가 개인 이익을 위해서 페미니즘같은 문제점을 외면하지않고 맞선 용기와 확실한 국가관 및 안보관 그리고 ''썩어빠진''' 보수의 정신을 고치기위한 공정 경쟁 때문이다", "대상하이라이트": "''보수틀딱'''들아...니들은 정말 보수냐? 아니면 민주딩 쁘락치냐? 혹은 기회주의자에게 선동당한 사이비 신도냐?#@이름# #@이름# #@이름#등이 하는 행동들이 보수같냐 #@이름#이 보수같냐?제발 정신 좀 차려라.정권교체 하고싶다며?지금 니들은 대놓고 빨갱이 짓 안하는 #@이름#을 대통영으로 만드려는거다. 그리고 대깨문이 하는 짓을 똑같이 따라라며 보수 지지율 박살내는거다 #@이름#이 지지받는 이유가 개인 이익을 위해서 페미니즘같은 문제점을 외면하지않고 맞선 용기와 확실한 국가관 및 안보관 그리고 썩어빠진 보수의 정신을 고치기위한 공정 경쟁 때문이다", "정치성향Y/N": "Y", "혐오 클래스": "Y", "특정 집단": "N", "그 외": "N"}