{"모욕": 1, "욕설": 1, "외설": 0, "폭력위협/범죄조장": 0, "성혐오": 0, "연령": 0, "인종/지역": 0, "장애": 0, "종교": 0, "정치성향": 1, "직업": 0, "1단계Y/N": "Y", "2-1단계Y/N": "Y", "2-2단계Y/N": "Y", "문장": "윤씨나 #@이름# 거게그거지 정부정책가지고 이슈을만든 그''넘'''이 그''넘'''이고 군대복무 미필자가 할말있나 군데목무미필자가 이래라 저래라 하지마라 지겨운 ''쑤구레'''같은니 너같은 ''인간'''들 살면서 많이뵈다 저는안하고 남보고하라고", "대상하이라이트": "''윤씨'''나 ''#@이름#''' 거게그거지 정부정책가지고 이슈을만든 그넘이 그넘이고 군대복무 미필자가 할말있나 군데목무미필자가 이래라 저래라 하지마라 지겨운 쑤구레같은니 너같은 인간들 살면서 많이뵈다 저는안하고 남보고하라고", "정치성향Y/N": "Y", "혐오 클래스": "Y", "특정 집단": "N", "그 외": "N"}