{"모욕": 2, "욕설": 0, "외설": 0, "폭력위협/범죄조장": 2, "성혐오": 0, "연령": 0, "인종/지역": 0, "장애": 0, "종교": 0, "정치성향": 0, "직업": 0, "1단계Y/N": "Y", "2-1단계Y/N": "Y", "2-2단계Y/N": "Y", "문장": "내가 너를 고소하고 싶어 #@이름#아 진짜 ''존나''' ''패고싶다''' 생각이없니? ''국뽕'''으로 뭘하든 오냐오냐 해주니가 뭐든 니 멋대로 해도 되는것 같아? 공항에는 꼬박꼬박 마스크 끼고 오는''놈'''이 놀러다닐땐 마스크도 안쓰고 진짜 서운하다 #@이름#아", "대상하이라이트": "내가 너를 고소하고 싶어 ''#@이름#'''아 진짜 존나 패고싶다 생각이없니? 국뽕으로 뭘하든 오냐오냐 해주니가 뭐든 니 멋대로 해도 되는것 같아? 공항에는 꼬박꼬박 마스크 끼고 오는놈이 놀러다닐땐 마스크도 안쓰고 진짜 서운하다 ''#@이름#'''아", "혐오 클래스": "Y", "특정 집단": "N", "그 외": "N"}